Workbook
Name Stocks: #REF!

Sheet Dashboard
B1: =TODAY() -> 46241
B2: Performance vs Benchmarks | C2: Daily Change | D2: Total Change | G2: Date | H2: NAV/share
B3: Offshore Fund | C3: ='Portfolio Snapshot'!E24 -> #DIV/0! | D3: =INDEX(NAV!I:I,MATCH(Dashboard!G3,NAV!B:B,0)) -> 0 | G3: =B1-1 -> 46240 | H3: =INDEX(NAV!G:G,MATCH(Dashboard!G3,NAV!B:B,0)) -> 0
B4: MSCI World Index | C4: ='Daily Change'!E38 -> -0.0024862539 | D4: =INDEX(NAV!L:L,MATCH(Dashboard!G3,NAV!B:B,0)) -> 0
B6: Securities | C6: Daily Change | D6: Total Return | E6: Status | F6: Strategic % Allocation | G6: Current % Allocation | H6: Strategic $ Allocation | I6: Current $ Allocation | J6: $ Difference
B7: Market/Large Cap
B8: Developed Economies (ex US) | C8: =IFERROR(VLOOKUP(B8,'Portfolio Allocation'!A:J,10,FALSE),"") -> 0 | D8: =IFERROR(VLOOKUP(B8,'Portfolio Allocation'!A:L,11,FALSE)," ") -> 0.1052609 | E8: =VLOOKUP(B8,'Portfolio Allocation'!A:H,3,FALSE) -> Overweight | F8: =VLOOKUP(B8,'Portfolio Allocation'!A:D,4,FALSE) -> 0.07 | G8: =VLOOKUP(B8,'Portfolio Allocation'!A:E,5,FALSE) -> 0.1771776 | H8: =VLOOKUP(B8,'Portfolio Allocation'!A:G,6,FALSE) -> 52499.611 | I8: =VLOOKUP(B8,'Portfolio Allocation'!A:G,7,FALSE) -> 132883.2 | J8: =I8-H8 -> 80383.589
B9: US Large Cap value | C9: =IFERROR(VLOOKUP(B9,'Portfolio Allocation'!A:J,10,FALSE),"") -> -0.0027679807 | D9: =IFERROR(VLOOKUP(B9,'Portfolio Allocation'!A:L,11,FALSE)," ") -> 0.38144604 | E9: =VLOOKUP(B9,'Portfolio Allocation'!A:H,3,FALSE) -> Underweight | F9: =VLOOKUP(B9,'Portfolio Allocation'!A:D,4,FALSE) -> 0.07 | G9: =VLOOKUP(B9,'Portfolio Allocation'!A:E,5,FALSE) -> 0.055097933 | H9: =VLOOKUP(B9,'Portfolio Allocation'!A:G,6,FALSE) -> 52499.611 | I9: =VLOOKUP(B9,'Portfolio Allocation'!A:G,7,FALSE) -> 41323.45 | J9: =I9-H9 -> -11176.161
B10: Microsoft | C10: =IFERROR(VLOOKUP(B10,'Portfolio Allocation'!A:J,10,FALSE),"") -> 0.025437985 | D10: =IFERROR(VLOOKUP(B10,'Portfolio Allocation'!A:L,11,FALSE)," ") -> 0.2318644 | E10: =VLOOKUP(B10,'Portfolio Allocation'!A:H,3,FALSE) -> Underweight | F10: =VLOOKUP(B10,'Portfolio Allocation'!A:D,4,FALSE) -> 0.06 | G10: =VLOOKUP(B10,'Portfolio Allocation'!A:E,5,FALSE) -> 0.01466256 | H10: =VLOOKUP(B10,'Portfolio Allocation'!A:G,6,FALSE) -> 44999.666 | I10: =VLOOKUP(B10,'Portfolio Allocation'!A:G,7,FALSE) -> 10996.92 | J10: =I10-H10 -> -34002.746
B11: Europe | C11: =IFERROR(VLOOKUP(B11,'Portfolio Allocation'!A:J,10,FALSE),"") -> 0 | D11: =IFERROR(VLOOKUP(B11,'Portfolio Allocation'!A:L,11,FALSE)," ") -> 0.29115424 | E11: =VLOOKUP(B11,'Portfolio Allocation'!A:H,3,FALSE) -> Underweight | F11: =VLOOKUP(B11,'Portfolio Allocation'!A:D,4,FALSE) -> 0.07 | G11: =VLOOKUP(B11,'Portfolio Allocation'!A:E,5,FALSE) -> 0.0180424 | H11: =VLOOKUP(B11,'Portfolio Allocation'!A:G,6,FALSE) -> 52499.611 | I11: =VLOOKUP(B11,'Portfolio Allocation'!A:G,7,FALSE) -> 13531.8 | J11: =I11-H11 -> -38967.811
B12: Nvidia Corp | C12: =IFERROR(VLOOKUP(B12,'Portfolio Allocation'!A:J,10,FALSE),"") -> -0.0010491743 | D12: =IFERROR(VLOOKUP(B12,'Portfolio Allocation'!A:L,11,FALSE)," ") -> 0.56557855 | E12: =VLOOKUP(B12,'Portfolio Allocation'!A:H,3,FALSE) -> Underweight | F12: =VLOOKUP(B12,'Portfolio Allocation'!A:D,4,FALSE) -> 0.06 | G12: =VLOOKUP(B12,'Portfolio Allocation'!A:E,5,FALSE) -> 0.02452688 | H12: =VLOOKUP(B12,'Portfolio Allocation'!A:G,6,FALSE) -> 44999.666 | I12: =VLOOKUP(B12,'Portfolio Allocation'!A:G,7,FALSE) -> 18395.16 | J12: =I12-H12 -> -26604.506
F13: =SUM(F8:F11) -> 0.27 | G13: =SUM(G8:G11) -> 0.26498049 | H13: =SUM(H8:H11) -> 202498.5 | I13: =SUM(I8:I12) -> 217130.53 | J13: =I13-H13 -> 14632.031
B14: Small Cap
B15: Growth | C15: =IFERROR(VLOOKUP(B15,'Portfolio Allocation'!A:J,10,FALSE),"") -> 0 | D15: =IFERROR(VLOOKUP(B15,'Portfolio Allocation'!A:L,11,FALSE)," ") -> 0.36090985 | E15: =VLOOKUP(B15,'Portfolio Allocation'!A:H,3,FALSE) -> Underweight | F15: =VLOOKUP(B15,'Portfolio Allocation'!A:D,4,FALSE) -> 0.07 | G15: =VLOOKUP(B15,'Portfolio Allocation'!A:E,5,FALSE) -> 0.068057427 | H15: =VLOOKUP(B15,'Portfolio Allocation'!A:G,6,FALSE) -> 52499.611 | I15: =VLOOKUP(B15,'Portfolio Allocation'!A:G,7,FALSE) -> 51043.07 | J15: =I15-H15 -> -1456.5408
F16: =SUM(F15:F15) -> 0.07 | G16: =SUM(G15:G15) -> 0.068057427 | H16: =SUM(H15:H15) -> 52499.611 | I16: =SUM(I15:I15) -> 51043.07 | J16: =I16-H16 -> -1456.5408
B17: Theta/Income/Dividend
B18: Alpha Architect 1-3 Month Box ET | C18: =IFERROR(VLOOKUP(B18,'Portfolio Allocation'!A:J,10,FALSE),"") -> 0.00016992353 | D18: =IFERROR(VLOOKUP(B18,'Portfolio Allocation'!A:L,11,FALSE)," ") -> 0.0032998883 | E18: =VLOOKUP(B18,'Portfolio Allocation'!A:H,3,FALSE) -> Overweight | F18: =VLOOKUP(B18,'Portfolio Allocation'!A:D,4,FALSE) -> 0.03 | G18: =VLOOKUP(B18,'Portfolio Allocation'!A:E,5,FALSE) -> 0.3814128 | H18: =VLOOKUP(B18,'Portfolio Allocation'!A:G,6,FALSE) -> 22499.833 | I18: =VLOOKUP(B18,'Portfolio Allocation'!A:G,7,FALSE) -> 286059.6 | J18: =I18-H18 -> 263559.77
F19: =SUM(F18:F18) -> 0.03 | G19: =SUM(G18:G18) -> 0.3814128 | H19: =SUM(H18:H18) -> 22499.833 | I19: =SUM(I18:I18) -> 286059.6 | J19: =I19-H19 -> 263559.77
B20: Momentum/Trend Following
B21: Digi Power X | C21: =IFERROR(VLOOKUP(B21,'Portfolio Allocation'!A:J,10,FALSE),"") -> 0 | D21: =IFERROR(VLOOKUP(B21,'Portfolio Allocation'!A:L,11,FALSE)," ") -> -0.57765378 | E21: =VLOOKUP(B21,'Portfolio Allocation'!A:H,3,FALSE) -> Underweight | F21: =VLOOKUP(B21,'Portfolio Allocation'!A:D,4,FALSE) -> 0.03 | G21: =VLOOKUP(B21,'Portfolio Allocation'!A:E,5,FALSE) -> 0.0175 | H21: =VLOOKUP(B21,'Portfolio Allocation'!A:G,6,FALSE) -> 22499.833 | I21: =VLOOKUP(B21,'Portfolio Allocation'!A:G,7,FALSE) -> 13125 | J21: =I21-H21 -> -9374.8332
B22: Wolfspeed | C22: =IFERROR(VLOOKUP(B22,'Portfolio Allocation'!A:J,10,FALSE),"") -> 0.095275903 | D22: =IFERROR(VLOOKUP(B22,'Portfolio Allocation'!A:L,11,FALSE)," ") -> -0.6106211 | E22: =VLOOKUP(B22,'Portfolio Allocation'!A:H,3,FALSE) -> Underweight | F22: =VLOOKUP(B22,'Portfolio Allocation'!A:D,4,FALSE) -> 0.03 | G22: =VLOOKUP(B22,'Portfolio Allocation'!A:E,5,FALSE) -> 0.022072 | H22: =VLOOKUP(B22,'Portfolio Allocation'!A:G,6,FALSE) -> 22499.833 | I22: =VLOOKUP(B22,'Portfolio Allocation'!A:G,7,FALSE) -> 16554 | J22: =I22-H22 -> -5945.8332
B23: On Semiconductor | C23: =IFERROR(VLOOKUP(B23,'Portfolio Allocation'!A:J,10,FALSE),"") -> 0.018463139 | D23: =IFERROR(VLOOKUP(B23,'Portfolio Allocation'!A:L,11,FALSE)," ") -> -0.22954098 | E23: =VLOOKUP(B23,'Portfolio Allocation'!A:H,3,FALSE) -> Underweight | F23: =VLOOKUP(B23,'Portfolio Allocation'!A:D,4,FALSE) -> 0.03 | G23: =VLOOKUP(B23,'Portfolio Allocation'!A:E,5,FALSE) -> 0.0250656 | H23: =VLOOKUP(B23,'Portfolio Allocation'!A:G,6,FALSE) -> 22499.833 | I23: =VLOOKUP(B23,'Portfolio Allocation'!A:G,7,FALSE) -> 18799.2 | J23: =I23-H23 -> -3700.6332
F24: =SUM(F21:F23) -> 0.09 | G24: =SUM(G21:G23) -> 0.0646376 | H24: =SUM(H21:H23) -> 67499.5 | I24: =SUM(I21:I23) -> 48478.2 | J24: =I24-H24 -> -19021.3
B25: Value/Quality
B27: JPMorgan Chase & Co | C27: =IFERROR(VLOOKUP(B27,'Portfolio Allocation'!A:J,10,FALSE),"") -> -0.0081839439 | D27: =IFERROR(VLOOKUP(B27,'Portfolio Allocation'!A:L,11,FALSE)," ") -> 0.2705702 | E27: =VLOOKUP(B27,'Portfolio Allocation'!A:H,3,FALSE) -> Underweight | F27: =VLOOKUP(B27,'Portfolio Allocation'!A:D,4,FALSE) -> 0.02 | G27: =VLOOKUP(B27,'Portfolio Allocation'!A:E,5,FALSE) -> 0.0171024 | H27: =VLOOKUP(B27,'Portfolio Allocation'!A:G,6,FALSE) -> 14999.889 | I27: =VLOOKUP(B27,'Portfolio Allocation'!A:G,7,FALSE) -> 12826.8 | J27: =I27-H27 -> -2173.0888
B28: Texas Instrument | C28: =IFERROR(VLOOKUP(B28,'Portfolio Allocation'!A:J,10,FALSE),"") -> 0.0024485093 | D28: =IFERROR(VLOOKUP(B28,'Portfolio Allocation'!A:L,11,FALSE)," ") -> -0.065602974 | E28: =VLOOKUP(B28,'Portfolio Allocation'!A:H,3,FALSE) -> Overweight | F28: =VLOOKUP(B28,'Portfolio Allocation'!A:D,4,FALSE) -> 0.03 | G28: =VLOOKUP(B28,'Portfolio Allocation'!A:E,5,FALSE) -> 0.048256 | H28: =VLOOKUP(B28,'Portfolio Allocation'!A:G,6,FALSE) -> 22499.833 | I28: =VLOOKUP(B28,'Portfolio Allocation'!A:G,7,FALSE) -> 36192 | J28: =I28-H28 -> 13692.167
B29: Amazon.com | C29: =IFERROR(VLOOKUP(B29,'Portfolio Allocation'!A:J,10,FALSE),"") -> -0.0014304053 | D29: =IFERROR(VLOOKUP(B29,'Portfolio Allocation'!A:L,11,FALSE)," ") -> 0.26492366 | E29: =VLOOKUP(B29,'Portfolio Allocation'!A:H,3,FALSE) -> Overweight | F29: =VLOOKUP(B29,'Portfolio Allocation'!A:D,4,FALSE) -> 0.02 | G29: =VLOOKUP(B29,'Portfolio Allocation'!A:E,5,FALSE) -> 0.025410933 | H29: =VLOOKUP(B29,'Portfolio Allocation'!A:G,6,FALSE) -> 14999.889 | I29: =VLOOKUP(B29,'Portfolio Allocation'!A:G,7,FALSE) -> 19058.2 | J29: =I29-H29 -> 4058.3112
B30: PDF Solutions | C30: =IFERROR(VLOOKUP(B30,'Portfolio Allocation'!A:J,10,FALSE),"") -> -0.071977355 | D30: =IFERROR(VLOOKUP(B30,'Portfolio Allocation'!A:L,11,FALSE)," ") -> 0.034329449 | E30: =VLOOKUP(B30,'Portfolio Allocation'!A:H,3,FALSE) -> Overweight | F30: =VLOOKUP(B30,'Portfolio Allocation'!A:D,4,FALSE) -> 0.03 | G30: =VLOOKUP(B30,'Portfolio Allocation'!A:E,5,FALSE) -> 0.067932 | H30: =VLOOKUP(B30,'Portfolio Allocation'!A:G,6,FALSE) -> 22499.833 | I30: =VLOOKUP(B30,'Portfolio Allocation'!A:G,7,FALSE) -> 50949 | J30: =I30-H30 -> 28449.167
B31: Ciena Corp | C31: =IFERROR(VLOOKUP(B31,'Portfolio Allocation'!A:J,10,FALSE),"") -> -0.012401243 | D31: =IFERROR(VLOOKUP(B31,'Portfolio Allocation'!A:L,11,FALSE)," ") -> -0.25653827 | E31: =VLOOKUP(B31,'Portfolio Allocation'!A:H,3,FALSE) -> Underweight | F31: =VLOOKUP(B31,'Portfolio Allocation'!A:D,4,FALSE) -> 0.03 | G31: =VLOOKUP(B31,'Portfolio Allocation'!A:E,5,FALSE) -> 0.019918827 | H31: =VLOOKUP(B31,'Portfolio Allocation'!A:G,6,FALSE) -> 22499.833 | I31: =VLOOKUP(B31,'Portfolio Allocation'!A:G,7,FALSE) -> 14939.12 | J31: =I31-H31 -> -7560.7132
B32: Lumentum Holdings | C32: =IFERROR(VLOOKUP(B32,'Portfolio Allocation'!A:J,10,FALSE),"") -> 0.014281219 | D32: =IFERROR(VLOOKUP(B32,'Portfolio Allocation'!A:L,11,FALSE)," ") -> -0.081074561 | E32: =VLOOKUP(B32,'Portfolio Allocation'!A:H,3,FALSE) -> Underweight | F32: =VLOOKUP(B32,'Portfolio Allocation'!A:D,4,FALSE) -> 0.03 | G32: =VLOOKUP(B32,'Portfolio Allocation'!A:E,5,FALSE) -> 0.022348267 | H32: =VLOOKUP(B32,'Portfolio Allocation'!A:G,6,FALSE) -> 22499.833 | I32: =VLOOKUP(B32,'Portfolio Allocation'!A:G,7,FALSE) -> 16761.2 | J32: =I32-H32 -> -5738.6332
F33: =SUM(F26:F32) -> 0.16 | H33: =SUM(H26:H32) -> 119999.11 | I33: =SUM(I26:I32) -> 150726.32 | J33: =I33-H33 -> 30727.21
B34: Others
B35: Cash | C35: =IFERROR(VLOOKUP(B35,'Portfolio Allocation'!A:J,10,FALSE),"") | D35: =IFERROR(VLOOKUP(B35,'Portfolio Allocation'!A:L,11,FALSE)," ") | E35: =VLOOKUP(B35,'Portfolio Allocation'!A:H,3,FALSE) -> Overweight | F35: =VLOOKUP(B35,'Portfolio Allocation'!A:D,4,FALSE) -> 0 | G35: =VLOOKUP(B35,'Portfolio Allocation'!A:E,5,FALSE) -> 0.12053004 | H35: =VLOOKUP(B35,'Portfolio Allocation'!A:G,6,FALSE) -> 0 | I35: =VLOOKUP(B35,'Portfolio Allocation'!A:G,7,FALSE) -> 90397.53 | J35: =I35-H35 -> 90397.53
B36: Total | F36: =SUM(F16,F13,F19,F24,F33,F35) -> 0.62 | G36: =SUM(G16,G13,G19,G24,G33,G35) -> 0.89961836 | H36: =SUM(H16,H13,H19,H24,H33,H35) -> 464996.55 | I36: =SUM(I16,I13,I19,I24,I33,I35) -> 843835.25 | J36: =SUM(J16,J13,J19,J24,J33,J35) -> 378838.7

Sheet Portfolio Snapshot
A1: SYMBOL | B1: PRICE | C1: UNITS | D1: CURRENT VALUE | E1: WAC | F1: COST | G1: Dividends | H1: P or L | I1: WEIGHT | J1: BETA | K1: WEIGHTED BETA | L1: % RETURN | M1: INDUSTRY | N1: EXPOSURE | O1: WEIGHTED RETURN | P1: WEIGHTED BETA | Q1: SECTOR | R1: # COMPANIES
A2: IDEV | B2: =_xlfn.XLOOKUP(A2,'Daily Change'!A:A,'Daily Change'!C:C,,0) -> 92.28 | C2: =IFERROR(VLOOKUP(A2,Ledger!$J$3:$L$30,2,FALSE),0) -> 1440 | D2: =C2*B2 -> 132883.2 | E2: =IFERROR(VLOOKUP(A2,Ledger!$J$3:$L$30,3,FALSE),0) -> 83.772201 | F2: =E2*C2 -> 120631.97 | G2: =304.35+142.25 -> 446.6 | H2: =D2-F2+G2 -> 12697.83 | I2: =D2/$D$19 -> 0.13238098 | J2: =VLOOKUP(A:A,'Daily Change'!A:F,6,) -> 0.9599 | K2: =J2*I2 -> 0.12707251 | L2: =H2/F2 -> 0.1052609 | M2: Diversified ETFs | N2: {=SUMPRODUCT(($Q$2:$Q$18=M2)*$D$2:$D$18)/$D$19} -> 0.23787907 | O2: {=IFERROR(SUMPRODUCT(($Q$2:$Q$18=M2)*$H$2:$H$18)/SUMPRODUCT(($Q$2:$Q$18=M2)*$F$2:$F$18),0)} -> 0.20509962 | P2: {=IFERROR(SUMPRODUCT(($Q$2:$Q$18=M2)*$D$2:$D$18*$J$2:$J$18)/SUMPRODUCT(($Q$2:$Q$18=M2)*$D$2:$D$18),0)} -> 0.94683449 | Q2: Diversified ETFs | R2: =COUNTIF($Q$2:$Q$18,M2) -> 4
A3: MSFT | B3: =_xlfn.XLOOKUP(A3,'Daily Change'!A:A,'Daily Change'!C:C,,0) -> 499.86 | C3: =IFERROR(VLOOKUP(A3,Ledger!$J$3:$L$30,2,FALSE),0) -> 22 | D3: =C3*B3 -> 10996.92 | E3: =IFERROR(VLOOKUP(A3,Ledger!$J$3:$L$30,3,FALSE),0) -> 406.20136 | F3: =E3*C3 -> 8936.43 | G3: 11.55 | H3: =D3-F3+G3 -> 2072.04 | I3: =D3/$D$19 -> 0.010955358 | J3: =VLOOKUP(A:A,'Daily Change'!A:F,6,) -> 1.1022 | K3: =J3*I3 -> 0.012074996 | L3: =H3/F3 -> 0.2318644 | M3: Software/Cloud | N3: {=SUMPRODUCT(($Q$2:$Q$18=M3)*$D$2:$D$18)/$D$19} -> 0.093292315 | O3: {=IFERROR(SUMPRODUCT(($Q$2:$Q$18=M3)*$H$2:$H$18)/SUMPRODUCT(($Q$2:$Q$18=M3)*$F$2:$F$18),0)} -> -0.029738803 | P3: {=IFERROR(SUMPRODUCT(($Q$2:$Q$18=M3)*$D$2:$D$18*$J$2:$J$18)/SUMPRODUCT(($Q$2:$Q$18=M3)*$D$2:$D$18),0)} -> 1.5091111 | Q3: Software/Cloud | R3: =COUNTIF($Q$2:$Q$18,M3) -> 4
A4: VOT | B4: =_xlfn.XLOOKUP(A4,'Daily Change'!A:A,'Daily Change'!C:C,,0) -> 302.03 | C4: =IFERROR(VLOOKUP(A4,Ledger!$J$3:$L$30,2,FALSE),0) -> 169 | D4: =C4*B4 -> 51043.07 | E4: =IFERROR(VLOOKUP(A4,Ledger!$J$3:$L$30,3,FALSE),0) -> 222.16467 | F4: =E4*C4 -> 37545.83 | G4: 53.42 | H4: =D4-F4+G4 -> 13550.66 | I4: =D4/$D$19 -> 0.050850159 | J4: =VLOOKUP(A:A,'Daily Change'!A:F,6,) -> 0.9247 | K4: =J4*I4 -> 0.047021142 | L4: =H4/F4 -> 0.36090985 | M4: Cash/Fixed Income | N4: {=SUMPRODUCT(($Q$2:$Q$18=M4)*$D$2:$D$18)/$D$19} -> 0.28497847 | O4: {=IFERROR(SUMPRODUCT(($Q$2:$Q$18=M4)*$H$2:$H$18)/SUMPRODUCT(($Q$2:$Q$18=M4)*$F$2:$F$18),0)} -> 0.0032998883 | P4: {=IFERROR(SUMPRODUCT(($Q$2:$Q$18=M4)*$D$2:$D$18*$J$2:$J$18)/SUMPRODUCT(($Q$2:$Q$18=M4)*$D$2:$D$18),0)} -> 0.4974 | Q4: Diversified ETFs | R4: =COUNTIF($Q$2:$Q$18,M4) -> 1
A5: VTV | B5: =_xlfn.XLOOKUP(A5,'Daily Change'!A:A,'Daily Change'!C:C,,0) -> 223.37 | C5: =IFERROR(VLOOKUP(A5,Ledger!$J$3:$L$30,2,FALSE),0) -> 185 | D5: =C5*B5 -> 41323.45 | E5: =IFERROR(VLOOKUP(A5,Ledger!$J$3:$L$30,3,FALSE),0) -> 162.20622 | F5: =E5*C5 -> 30008.15 | G5: 131.19 | H5: =D5-F5+G5 -> 11446.49 | I5: =D5/$D$19 -> 0.041167273 | J5: =VLOOKUP(A:A,'Daily Change'!A:F,6,) -> 0.886 | K5: =J5*I5 -> 0.036474204 | L5: =H5/F5 -> 0.38144604 | M5: E-Commerce/Internet | N5: {=SUMPRODUCT(($Q$2:$Q$18=M5)*$D$2:$D$18)/$D$19} -> 0.018986172 | O5: {=IFERROR(SUMPRODUCT(($Q$2:$Q$18=M5)*$H$2:$H$18)/SUMPRODUCT(($Q$2:$Q$18=M5)*$F$2:$F$18),0)} -> 0.26492366 | P5: {=IFERROR(SUMPRODUCT(($Q$2:$Q$18=M5)*$D$2:$D$18*$J$2:$J$18)/SUMPRODUCT(($Q$2:$Q$18=M5)*$D$2:$D$18),0)} -> 1.447 | Q5: Diversified ETFs | R5: =COUNTIF($Q$2:$Q$18,M5) -> 1
A6: NVDA | B6: =_xlfn.XLOOKUP(A6,'Daily Change'!A:A,'Daily Change'!C:C,,0) -> 218.99 | C6: =IFERROR(VLOOKUP(A6,Ledger!$J$3:$L$233,2,FALSE),0) -> 84 | D6: =C6*B6 -> 18395.16 | E6: =IFERROR(VLOOKUP(A6,Ledger!$J$3:$L$233,3,FALSE),0) -> 139.89131 | F6: =E6*C6 -> 11750.87 | G6: 1.75 | H6: =D6-F6+G6 -> 6646.04 | I6: =D6/$D$19 -> 0.018325638 | J6: =VLOOKUP(A:A,'Daily Change'!A:F,6,) -> 2.2139 | K6: =J6*I6 -> 0.040571129 | L6: =H6/F6 -> 0.56557855 | M6: Financials | N6: {=SUMPRODUCT(($Q$2:$Q$18=M6)*$D$2:$D$18)/$D$19} -> 0.012778323 | O6: {=IFERROR(SUMPRODUCT(($Q$2:$Q$18=M6)*$H$2:$H$18)/SUMPRODUCT(($Q$2:$Q$18=M6)*$F$2:$F$18),0)} -> 0.2705702 | P6: {=IFERROR(SUMPRODUCT(($Q$2:$Q$18=M6)*$D$2:$D$18*$J$2:$J$18)/SUMPRODUCT(($Q$2:$Q$18=M6)*$D$2:$D$18),0)} -> 0.975 | Q6: Semiconductors | R6: =COUNTIF($Q$2:$Q$18,M6) -> 1
A7: FEZ | B7: =_xlfn.XLOOKUP(A7,'Daily Change'!A:A,'Daily Change'!C:C,,0) -> 71.22 | C7: =IFERROR(VLOOKUP(A7,Ledger!$J$3:$L$30,2,FALSE),0) -> 190 | D7: =C7*B7 -> 13531.8 | E7: =IFERROR(VLOOKUP(A7,Ledger!$J$3:$L$30,3,FALSE),0) -> 55.159947 | F7: =E7*C7 -> 10480.39 | G7: 0 | H7: =D7-F7+G7 -> 3051.41 | I7: =D7/$D$19 -> 0.013480658 | J7: =VLOOKUP(A:A,'Daily Change'!A:F,6,) -> 1.0878 | K7: =J7*I7 -> 0.01466426 | L7: =H7/F7 -> 0.29115424 | M7: Utilities / AI Infra | N7: {=SUMPRODUCT(($Q$2:$Q$18=M7)*$D$2:$D$18)/$D$19} -> 0.013075396 | O7: {=IFERROR(SUMPRODUCT(($Q$2:$Q$18=M7)*$H$2:$H$18)/SUMPRODUCT(($Q$2:$Q$18=M7)*$F$2:$F$18),0)} -> -0.57765378 | P7: {=IFERROR(SUMPRODUCT(($Q$2:$Q$18=M7)*$D$2:$D$18*$J$2:$J$18)/SUMPRODUCT(($Q$2:$Q$18=M7)*$D$2:$D$18),0)} -> 7.0902 | Q7: Diversified ETFs | R7: =COUNTIF($Q$2:$Q$18,M7) -> 1
A8: JPM | B8: =_xlfn.XLOOKUP(A8,'Daily Change'!A:A,'Daily Change'!C:C,,0) -> 356.3 | C8: =IFERROR(VLOOKUP(A8,Ledger!$J$3:$L$20,2,FALSE),0) -> 36 | D8: =C8*B8 -> 12826.8 | E8: =IFERROR(VLOOKUP(A8,Ledger!$J$3:$L$20,3,FALSE),0) -> 280.42528 | F8: =E8*C8 -> 10095.31 | G8: 0 | H8: =D8-F8+G8 -> 2731.49 | I8: =D8/$D$19 -> 0.012778323 | J8: =VLOOKUP(A:A,'Daily Change'!A:F,6,) -> 0.975 | K8: =J8*I8 -> 0.012458865 | L8: =H8/F8 -> 0.2705702 | Q8: Financials
A9: AMZN | B9: =_xlfn.XLOOKUP(A9,'Daily Change'!A:A,'Daily Change'!C:C,,0) -> 272.26 | C9: =IFERROR(VLOOKUP(A9,Ledger!$J$3:$L$22,2,FALSE),0) -> 70 | D9: =C9*B9 -> 19058.2 | E9: =IFERROR(VLOOKUP(A9,Ledger!$J$3:$L$22,3,FALSE),0) -> 215.23829 | F9: =E9*C9 -> 15066.68 | G9: 0 | H9: =D9-F9+G9 -> 3991.52 | I9: =D9/$D$19 -> 0.018986172 | J9: =VLOOKUP(A:A,'Daily Change'!A:F,6,) -> 1.447 | K9: =J9*I9 -> 0.027472991 | L9: =H9/F9 -> 0.26492366 | Q9: E-Commerce/Internet
A10: LITE | B10: =_xlfn.XLOOKUP(A10,'Daily Change'!A:A,'Daily Change'!C:C,,0) -> 838.06 | C10: =IFERROR(VLOOKUP(A10,Ledger!$J$3:$L$22,2,FALSE),0) -> 20 | D10: =C10*B10 -> 16761.2 | E10: =IFERROR(VLOOKUP(A10,Ledger!$J$3:$L$22,3,FALSE),0) -> 912 | F10: =E10*C10 -> 18240 | G10: 0 | H10: =D10-F10+G10 -> -1478.8 | I10: =D10/$D$19 -> 0.016697853 | J10: =VLOOKUP(A:A,'Daily Change'!A:F,6,) -> 1.5259 | K10: =J10*I10 -> 0.025479254 | L10: =H10/F10 -> -0.081074561 | Q10: Software/Cloud
A11: CIEN | B11: =_xlfn.XLOOKUP(A11,'Daily Change'!A:A,'Daily Change'!C:C,,0) -> 403.76 | C11: =IFERROR(VLOOKUP(A11,Ledger!$J$3:$L$31,2,FALSE),0) -> 37 | D11: =C11*B11 -> 14939.12 | E11: =IFERROR(VLOOKUP(A11,Ledger!$J$3:$L$31,3,FALSE),0) -> 543.08108 | F11: =E11*C11 -> 20094 | G11: 0 | H11: =D11-F11+G11 -> -5154.88 | I11: =D11/$D$19 -> 0.014882659 | J11: =VLOOKUP(A:A,'Daily Change'!A:F,6,) -> 1.3175 | K11: =J11*I11 -> 0.019607904 | L11: =H11/F11 -> -0.25653827 | Q11: Software/Cloud
A12: PDFS | B12: =_xlfn.XLOOKUP(A12,'Daily Change'!A:A,'Daily Change'!C:C,,0) -> 45.9 | C12: =IFERROR(VLOOKUP(A12,Ledger!$J$3:$L$237,2,FALSE),0) -> 1110 | D12: =C12*B12 -> 50949 | E12: =IFERROR(VLOOKUP(A12,Ledger!$J$3:$L$53,3,FALSE),0) -> 44.376577 | F12: =E12*C12 -> 49258 | G12: 0 | H12: =D12-F12+G12 -> 1691 | I12: =D12/$D$19 -> 0.050756444 | J12: =VLOOKUP(A:A,'Daily Change'!A:F,6,) -> 1.6476 | K12: =J12*I12 -> 0.083626318 | L12: =H12/F12 -> 0.034329449 | Q12: Software/Cloud
A13: ON | B13: =_xlfn.XLOOKUP(A13,'Daily Change'!A:A,'Daily Change'!C:C,,0) -> 78.33 | C13: =IFERROR(VLOOKUP(A13,Ledger!$J$3:$L$237,2,FALSE),0) -> 240 | D13: =C13*B13 -> 18799.2 | E13: =IFERROR(VLOOKUP(A13,Ledger!$J$3:$L$53,3,FALSE),0) -> 101.66667 | F13: =E13*C13 -> 24400 | G13: 0 | H13: =D13-F13+G13 -> -5600.8 | I13: =D13/$D$19 -> 0.018728151 | J13: =VLOOKUP(A:A,'Daily Change'!A:F,6,) -> 1.9949 | K13: =J13*I13 -> 0.037360788 | L13: =H13/F13 -> -0.22954098 | Q13: Semiconductors
A14: TXN | B14: =_xlfn.XLOOKUP(A14,'Daily Change'!A:A,'Daily Change'!C:C,,0) -> 278.4 | C14: =IFERROR(VLOOKUP(A14,Ledger!$J$3:$L$237,2,FALSE),0) -> 130 | D14: =C14*B14 -> 36192 | E14: =IFERROR(VLOOKUP(A14,Ledger!$J$3:$L$53,3,FALSE),0) -> 297.94615 | F14: =E14*C14 -> 38733 | G14: 0 | H14: =D14-F14+G14 -> -2541 | I14: =D14/$D$19 -> 0.036055217 | J14: =VLOOKUP(A:A,'Daily Change'!A:F,6,) -> 1.3201 | K14: =J14*I14 -> 0.047596491 | L14: =H14/F14 -> -0.065602974 | Q14: Semiconductors
A15: BOXX | B15: =_xlfn.XLOOKUP(A15,'Daily Change'!A:A,'Daily Change'!C:C,,0) -> 117.72 | C15: =IFERROR(VLOOKUP(A15,Ledger!$J$3:$L$237,2,FALSE),0) -> 2430 | D15: =C15*B15 -> 286059.6 | E15: =IFERROR(VLOOKUP(A15,Ledger!$J$3:$L$53,3,FALSE),0) -> 117.33281 | F15: =E15*C15 -> 285118.74 | G15: 0 | H15: =D15-F15+G15 -> 940.86 | I15: =D15/$D$19 -> 0.28497847 | J15: =VLOOKUP(A:A,'Daily Change'!A:F,6,) -> 0.4974 | K15: =J15*I15 -> 0.14174829 | L15: =H15/F15 -> 0.0032998883 | Q15: Cash/Fixed Income
A16: DGXX | B16: =_xlfn.XLOOKUP(A16,'Daily Change'!A:A,'Daily Change'!C:C,,0) -> 3.75 | C16: =IFERROR(VLOOKUP(A16,Ledger!$J$3:$L$237,2,FALSE),0) -> 3500 | D16: =(C16*B16) -> 13125 | E16: =IFERROR(VLOOKUP(A16,Ledger!$J$3:$L$53,3,FALSE),0) -> 8.8789714 | F16: =(E16*C16) -> 31076.4 | G16: 0 | H16: =D16-F16+G16 -> -17951.4 | I16: =D16/$D$19 -> 0.013075396 | J16: =VLOOKUP(A:A,'Daily Change'!A:F,6,) -> 7.0902 | K16: =J16*I16 -> 0.09270717 | L16: =H16/F16 -> -0.57765378 | Q16: Utilities / AI Infra
A17: URTH | B17: =_xlfn.XLOOKUP(A17,'Daily Change'!A:A,'Daily Change'!C:C,,0) -> 208.63 | C17: =IFERROR(VLOOKUP(A17,Ledger!$J$3:$L$237,2,FALSE),0) -> 1200 | D17: =(C17*B17) -> 250356 | E17: =IFERROR(VLOOKUP(A17,Ledger!$J$3:$L$53,3,FALSE),0) -> 201.74956 | F17: =(E17*C17) -> 242099.47 | G17: 0 | H17: =D17-F17+G17 -> 8256.53 | I17: =D17/$D$19 -> 0.24940981 | J17: =VLOOKUP(A:A,'Daily Change'!A:F,6,) -> 0 | K17: =J17*I17 -> 0 | L17: =H17/F17 -> 0.034103875
A18: WOLF | B18: =_xlfn.XLOOKUP(A18,'Daily Change'!A:A,'Daily Change'!C:C,,0) -> 27.59 | C18: =IFERROR(VLOOKUP(A18,Ledger!$J$3:$L$237,2,FALSE),0) -> 600 | D18: =(C18*B18) -> 16554 | E18: =IFERROR(VLOOKUP(A18,Ledger!$J$3:$L$53,3,FALSE),0) -> 70.856433 | F18: =(E18*C18) -> 42513.86 | G18: 0 | H18: =D18-F18+G18 -> -25959.86 | I18: =D18/$D$19 -> 0.016491436 | J18: =VLOOKUP(A:A,'Daily Change'!A:F,6,) -> 5.577 | K18: =J18*I18 -> 0.091972739 | L18: =H18/F18 -> -0.6106211 | Q18: Semiconductors
D19: =SUM(D2:D18) -> 1003793.7 | F19: =SUM(F2:F18) -> 996049.1 | G19: =SUM(G2:G18) -> 644.51 | H19: =SUM(H2:H18) -> 8389.13 | K19: =SUM(K2:K18) -> 0.85790905
C20: CASH VALUE AT HAND | D20: =Ledger!F117 -> 90397.53
C21: CURRENT PORTFOLIO VALUE | D21: =D20+D19 -> 1094191.2
C22: PREVIOUS PORTFOLIO VALUE | D22: =VLOOKUP(Dashboard!B1-1,NAV!B1:H800,4,FALSE) -> 0
C23: CASH INFLOW | D23: =IFERROR(INDEX(Subscription!$C$2:$C$1048576,MATCH(Dashboard!B1-1,Subscription!$A$2:$A$1048576,0)),0) -> 0
C24: CHANGE IN VALUE | D24: =D21-D22 -> 1094191.2 | E24: =D24/D22 -> #DIV/0!
B26: =_xlfn.XLOOKUP(A2,'Daily Change'!A:A,'Daily Change'!C:C,,0) -> 92.28

Sheet NAV
A1: Quarter | B1: Date | C1: Total Assets | D1: Total Liabilities | E1: Net Assets | F1: Shares Outstandings | G1: Nav | H1: Daily Return | I1: Total Return | J1: MSCI World | K1: MSCI World Daily Return | L1: MSCI World Total Return
A2: 3 | B2: 45475 | C2: 300000 | D2: 0 | E2: =C2-D2 -> 300000 | F2: 30000 | G2: =E2/F2 -> 10 | J2: 148.58
A3: 3 | B3: 45476 | C3: 298549.52 | D3: 0 | E3: =C3-D3 -> 298549.52 | F3: 30000 | G3: =E3/F3 -> 9.9516506 | H3: =G3/G2 -1 -> -0.0048349373 | I3: =G3/$G$2-1 -> -0.0048349373 | J3: 149.59 | K3: =J3/J2 -1 -> 0.0067976847 | L3: =J3/$J$2-1 -> 0.0067976847
A4: 3 | B4: 45477 | C4: 298549.52 | D4: 0 | E4: =C4-D4 -> 298549.52 | F4: 30000 | G4: =E4/F4 -> 9.9516506 | H4: =G4/G3 -1 -> 0 | I4: =G4/$G$2-1 -> -0.0048349373 | J4: 149.59 | K4: =J4/J3 -1 -> 0 | L4: =J4/$J$2-1 -> 0.0067976847
A5: 3 | B5: 45478 | C5: 298678.09 | D5: 0 | E5: =C5-D5 -> 298678.09 | F5: 30000 | G5: =E5/F5 -> 9.9559363 | H5: =G5/G4 -1 -> 0.00043064953 | I5: =G5/$G$2-1 -> -0.0044063699 | J5: 150.5 | K5: =J5/J4 -1 -> 0.0060832943 | L5: =J5/$J$2-1 -> 0.012922331
A6: 3 | B6: 45479 | C6: 298678.09 | D6: 0 | E6: =C6-D6 -> 298678.09 | F6: 30000 | G6: =E6/F6 -> 9.9559363 | H6: =G6/G5 -1 -> 0 | I6: =G6/$G$2-1 -> -0.0044063699 | J6: 150.5 | K6: =J6/J5 -1 -> 0 | L6: =J6/$J$2-1 -> 0.012922331
A7: 3 | B7: 45480 | C7: 298678.09 | D7: 0 | E7: =C7-D7 -> 298678.09 | F7: 30000 | G7: =E7/F7 -> 9.9559363 | H7: =G7/G6 -1 -> 0 | I7: =G7/$G$2-1 -> -0.0044063699 | J7: 150.5 | K7: =J7/J6 -1 -> 0 | L7: =J7/$J$2-1 -> 0.012922331
A8: 3 | B8: 45481 | C8: 298506.35 | D8: 0 | E8: =C8-D8 -> 298506.35 | F8: 30000 | G8: =E8/F8 -> 9.9502116 | H8: =G8/G7 -1 -> -0.00057500095 | I8: =G8/$G$2-1 -> -0.0049788372 | J8: 150.34 | K8: =J8/J7 -1 -> -0.0010631229 | L8: =J8/$J$2-1 -> 0.01184547
A9: 3 | B9: 45482 | C9: 298633.43 | D9: 0 | E9: =C9-D9 -> 298633.43 | F9: 30000 | G9: =E9/F9 -> 9.9544477 | H9: =G9/G8 -1 -> 0.00042572448 | I9: =G9/$G$2-1 -> -0.0045552324 | J9: 150.43 | K9: =J9/J8 -1 -> 0.00059864308 | L9: =J9/$J$2-1 -> 0.012451205
A10: 3 | B10: 45483 | C10: 299152.09 | D10: 0 | E10: =C10-D10 -> 299152.09 | F10: 30000 | G10: =E10/F10 -> 9.9717363 | H10: =G10/G9 -1 -> 0.0017367714 | I10: =G10/$G$2-1 -> -0.0028263723 | J10: 152.02 | K10: =J10/J9 -1 -> 0.0105697 | L10: =J10/$J$2-1 -> 0.02315251
A11: 3 | B11: 45484 | C11: 300519.64 | D11: 0 | E11: =C11-D11 -> 300519.64 | F11: 30000 | G11: =E11/F11 -> 10.017321 | H11: =G11/G10 -1 -> 0.0045714095 | I11: =G11/$G$2-1 -> 0.0017321167 | J11: 151.27 | K11: =J11/J10 -1 -> -0.0049335614 | L11: =J11/$J$2-1 -> 0.018104725
A12: 3 | B12: 45485 | C12: 301609.11 | D12: 0 | E12: =C12-D12 -> 301609.11 | F12: 30000 | G12: =E12/F12 -> 10.053637 | H12: =G12/G11 -1 -> 0.0036253039 | I12: =G12/$G$2-1 -> 0.0053637 | J12: 152.4 | K12: =J12/J11 -1 -> 0.0074700866 | L12: =J12/$J$2-1 -> 0.025710055
A13: 3 | B13: 45486 | C13: 301609.11 | D13: 0 | E13: =C13-D13 -> 301609.11 | F13: 30000 | G13: =E13/F13 -> 10.053637 | H13: =G13/G12 -1 -> 0 | I13: =G13/$G$2-1 -> 0.0053637 | J13: 152.4 | K13: =J13/J12 -1 -> 0 | L13: =J13/$J$2-1 -> 0.025710055
A14: 3 | B14: 45487 | C14: 301609.11 | D14: 0 | E14: =C14-D14 -> 301609.11 | F14: 30000 | G14: =E14/F14 -> 10.053637 | H14: =G14/G13 -1 -> 0 | I14: =G14/$G$2-1 -> 0.0053637 | J14: 152.4 | K14: =J14/J13 -1 -> 0 | L14: =J14/$J$2-1 -> 0.025710055
... A184: 4 | B184: 45657 | C184: 318232.56 | D184: 0 | E184: =C184-D184 -> 318232.56 | F184: 30000 | G184: =E184/F184 -> 10.607752 | H184: =G184/G183 -1 -> -0.0030662913 | I184: =G184/$G$2-1 -> 0.060775183 | J184: 155.5 | K184: =J184/J183 -1 -> -0.0039713041 | L184: =J184/$J$2-1 -> 0.046574236
A185: Quarter | B185: Date | C185: Total Assets | D185: Total Liabilities | E185: Net Assets | F185: Shares Outstandings | G185: Nav | H185: Daily Return | I185: Total Return | J185: MSCI World | K185: MSCI World Daily Return | L185: MSCI World Total Return
A186: 1 | B186: 45658 | C186: 318232.56 | D186: 0 | E186: =C186-D186 -> 318232.56 | F186: 30000 | G186: =E186/F186 -> 10.607752 | H186: =G186/G184 -1 -> 0 | I186: =G186/$G$186-1 -> 0 | J186: 155.5 | K186: =J186/J184 -1 -> 0 | L186: =J186/$J$186-1 -> 0
A187: 1 | B187: 45659 | C187: 318543.54 | D187: 0 | E187: =C187-D187 -> 318543.54 | F187: 30000 | G187: =E187/F187 -> 10.618118 | H187: =G187/G186 -1 -> 0.0009772256 | I187: =G187/$G$186-1 -> 0.0009772256 | J187: 155.2 | K187: =J187/J186 -1 -> -0.0019292605 | L187: =J187/$J$186-1 -> -0.0019292605
A188: 1 | B188: 45660 | C188: 321532.46 | D188: 0 | E188: =C188-D188 -> 321532.46 | F188: 30000 | G188: =E188/F188 -> 10.717749 | H188: =G188/G187 -1 -> 0.0093830815 | I188: =G188/$G$186-1 -> 0.010369476 | J188: 156.98 | K188: =J188/J187 -1 -> 0.011469072 | L188: =J188/$J$186-1 -> 0.0095176849
A189: 1 | B189: 45661 | C189: 321532.46 | D189: 0 | E189: =C189-D189 -> 321532.46 | F189: 30000 | G189: =E189/F189 -> 10.717749 | H189: =G189/G188 -1 -> 0 | I189: =G189/$G$186-1 -> 0.010369476 | J189: 156.98 | K189: =J189/J188 -1 -> 0 | L189: =J189/$J$186-1 -> 0.0095176849
A190: 1 | B190: 45662 | C190: 321532.46 | D190: 0 | E190: =C190-D190 -> 321532.46 | F190: 30000 | G190: =E190/F190 -> 10.717749 | H190: =G190/G189 -1 -> 0 | I190: =G190/$G$186-1 -> 0.010369476 | J190: 156.98 | K190: =J190/J189 -1 -> 0 | L190: =J190/$J$186-1 -> 0.0095176849
A191: 1 | B191: 45663 | C191: 322574.48 | D191: 0 | E191: =C191-D191 -> 322574.48 | F191: 30000 | G191: =E191/F191 -> 10.752483 | H191: =G191/G190 -1 -> 0.0032407925 | I191: =G191/$G$186-1 -> 0.013643874 | J191: 157.76 | K191: =J191/J190 -1 -> 0.0049687858 | L191: =J191/$J$186-1 -> 0.014533762
A192: 1 | B192: 45664 | C192: 320144.57 | D192: 0 | E192: =C192-D192 -> 320144.57 | F192: 30000 | G192: =E192/F192 -> 10.671485 | H192: =G192/G191 -1 -> -0.0075328805 | I192: =G192/$G$186-1 -> 0.0060082162 | J192: 156.41 | K192: =J192/J191 -1 -> -0.0085573022 | L192: =J192/$J$186-1 -> 0.00585209
A193: 1 | B193: 45665 | C193: 320573.75 | D193: 0 | E193: =C193-D193 -> 320573.75 | F193: 30000 | G193: =E193/F193 -> 10.685792 | H193: =G193/G192 -1 -> 0.0013405975 | I193: =G193/$G$186-1 -> 0.0073568683 | J193: 156.41 | K193: =J193/J192 -1 -> 0 | L193: =J193/$J$186-1 -> 0.00585209
A194: 1 | B194: 45666 | C194: 320573.75 | D194: 0 | E194: =C194-D194 -> 320573.75 | F194: 30000 | G194: =E194/F194 -> 10.685792 | H194: =G194/G193 -1 -> 0 | I194: =G194/$G$186-1 -> 0.0073568683 | J194: 156.41 | K194: =J194/J193 -1 -> 0 | L194: =J194/$J$186-1 -> 0.00585209
A195: 1 | B195: 45667 | C195: 317232.76 | D195: 0 | E195: =C195-D195 -> 317232.76 | F195: 30000 | G195: =E195/F195 -> 10.574425 | H195: =G195/G194 -1 -> -0.010421908 | I195: =G195/$G$186-1 -> -0.0031417119 | J195: 153 | K195: =J195/J194 -1 -> -0.021801675 | L195: =J195/$J$186-1 -> -0.01607717
A196: 1 | B196: 45668 | C196: 317232.76 | D196: 0 | E196: =C196-D196 -> 317232.76 | F196: 30000 | G196: =E196/F196 -> 10.574425 | H196: =G196/G195 -1 -> 0 | I196: =G196/$G$186-1 -> -0.0031417119 | J196: 153 | K196: =J196/J195 -1 -> 0 | L196: =J196/$J$186-1 -> -0.01607717
A197: 1 | B197: 45669 | C197: 317232.76 | D197: 0 | E197: =C197-D197 -> 317232.76 | F197: 30000 | G197: =E197/F197 -> 10.574425 | H197: =G197/G196 -1 -> 0 | I197: =G197/$G$186-1 -> -0.0031417119 | J197: 153 | K197: =J197/J196 -1 -> 0 | L197: =J197/$J$186-1 -> -0.01607717
A198: 1 | B198: 45670 | C198: 317295.62 | D198: 0 | E198: =C198-D198 -> 317295.62 | F198: 30000 | G198: =E198/F198 -> 10.576521 | H198: =G198/G197 -1 -> 0.00019815104 | I198: =G198/$G$186-1 -> -0.0029441834 | J198: 154.23 | K198: =J198/J197 -1 -> 0.0080392157 | L198: =J198/$J$186-1 -> -0.0081672026
... A550: 4 | B550: 46022 | C550: 452440.62 | D550: 0 | E550: =C550-D550 -> 452440.62 | F550: 39157 | G550: =E550/F550 -> 11.554527 | H550: =G550/G549 -1 -> -0.0063406641 | I550: =G550/$G$186-1 -> 0.089253156 | J550: 185.77 | K550: =J550/J549 -1 -> -0.0066306615 | L550: =J550/$J$186-1 -> 0.19466238
A551: Quarter | B551: Date | C551: Total Assets | D551: Total Liabilities | E551: Net Assets | F551: Shares Outstandings | G551: Nav | H551: Daily Return | I551: Total Return | J551: MSCI World | K551: MSCI World Daily Return | L551: MSCI World Total Return
A552: 1 | B552: 46023 | C552: 452440.62 | D552: 0 | E552: 452440.62 | F552: 39157 | G552: =E552/F552 -> 11.554527 | H552: =G552/G550-1 -> 0 | I552: =G552/$G$552-1 -> 0 | J552: 185.77 | K552: =J552/J550-1 -> 0 | L552: =J552/$J$552-1 -> 0
A553: 1 | B553: 46024 | C553: 453784 | D553: 0 | E553: =C553-D553 -> 453784 | F553: 39157 | G553: =E553/F553 -> 11.588835 | H553: =G553/G552-1 -> 0.0029691852 | I553: =G553/$G$552-1 -> 0.0029691852 | J553: 186.51 | K553: =J553/J552-1 -> 0.0039834204 | L553: =J553/$J$552-1 -> 0.0039834204
A554: 1 | B554: 46025 | C554: 453784 | D554: 0 | E554: =C554-D554 -> 453784 | F554: 39157 | G554: =E554/F554 -> 11.588835 | H554: =G554/G553-1 -> 0 | I554: =G554/$G$552-1 -> 0.0029691852 | J554: 186.51 | K554: =J554/J553-1 -> 0 | L554: =J554/$J$552-1 -> 0.0039834204
A555: 1 | B555: 46026 | C555: 453784 | D555: 0 | E555: =C555-D555 -> 453784 | F555: 39157 | G555: =E555/F555 -> 11.588835 | H555: =G555/G554-1 -> 0 | I555: =G555/$G$552-1 -> 0.0029691852 | J555: 186.51 | K555: =J555/J554-1 -> 0 | L555: =J555/$J$552-1 -> 0.0039834204
A556: 1 | B556: 46027 | C556: 457265.92 | D556: 0 | E556: =C556-D556 -> 457265.92 | F556: 39157 | G556: =E556/F556 -> 11.677757 | H556: =G556/G555-1 -> 0.0076730779 | I556: =G556/$G$552-1 -> 0.010665046 | J556: 188.01 | K556: =J556/J555-1 -> 0.0080424642 | L556: =J556/$J$552-1 -> 0.012057921
A557: 1 | B557: 46028 | C557: 461337.83 | D557: 0 | E557: =C557-D557 -> 461337.83 | F557: 39157 | G557: =E557/F557 -> 11.781746 | H557: =G557/G556-1 -> 0.0089049059 | I557: =G557/$G$552-1 -> 0.019664923 | J557: 188.98 | K557: =J557/J556-1 -> 0.0051593 | L557: =J557/$J$552-1 -> 0.017279432
A558: 1 | B558: 46029 | C558: 459040.37 | D558: 0 | E558: =C558-D558 -> 459040.37 | F558: 39157 | G558: =E558/F558 -> 11.723073 | H558: =G558/G557-1 -> -0.0049799948 | I558: =G558/$G$552-1 -> 0.014586997 | J558: 188.22 | K558: =J558/J557-1 -> -0.0040215896 | L558: =J558/$J$552-1 -> 0.013188351
A559: 1 | B559: 46030 | C559: 459407.46 | D559: 0 | E559: =C559-D559 -> 459407.46 | F559: 39157 | G559: =E559/F559 -> 11.732448 | H559: =G559/G558-1 -> 0.00079969001 | I559: =G559/$G$552-1 -> 0.015398352 | J559: 188.24 | K559: =J559/J558-1 -> 0.00010625863 | L559: =J559/$J$552-1 -> 0.013296011
A560: 1 | B560: 46031 | C560: 461799.72 | D560: 0 | E560: =C560-D560 -> 461799.72 | F560: 39157 | G560: =E560/F560 -> 11.793542 | H560: =G560/G559-1 -> 0.0052072729 | I560: =G560/$G$552-1 -> 0.020685808 | J560: 189.53 | K560: =J560/J559-1 -> 0.0068529537 | L560: =J560/$J$552-1 -> 0.020240082
A561: 1 | B561: 46032 | C561: 461799.72 | D561: 0 | E561: =C561-D561 -> 461799.72 | F561: 39157 | G561: =E561/F561 -> 11.793542 | H561: =G561/G560-1 -> 0 | I561: =G561/$G$552-1 -> 0.020685808 | J561: 189.53 | K561: =J561/J560-1 -> 0 | L561: =J561/$J$552-1 -> 0.020240082
A562: 1 | B562: 46033 | C562: 461799.72 | D562: 0 | E562: =C562-D562 -> 461799.72 | F562: 39157 | G562: =E562/F562 -> 11.793542 | H562: =G562/G561-1 -> 0 | I562: =G562/$G$552-1 -> 0.020685808 | J562: 189.53 | K562: =J562/J561-1 -> 0 | L562: =J562/$J$552-1 -> 0.020240082
A563: 1 | B563: 46034 | C563: 461413.55 | D563: 0 | E563: =C563-D563 -> 461413.55 | F563: 39157 | G563: =E563/F563 -> 11.78368 | H563: =G563/G562-1 -> -0.00083622831 | I563: =G563/$G$552-1 -> 0.019832282 | J563: 190.05 | K563: =J563/J562-1 -> 0.002743629 | L563: =J563/$J$552-1 -> 0.023039242
A564: 1 | B564: 46035 | C564: 460297.46 | D564: 0 | E564: =C564-D564 -> 460297.46 | F564: 39157 | G564: =E564/F564 -> 11.755177 | H564: =G564/G563-1 -> -0.0024188496 | I564: =G564/$G$552-1 -> 0.017365461 | J564: 189.53 | K564: =J564/J563-1 -> -0.0027361221 | L564: =J564/$J$552-1 -> 0.020240082
... A760: 30 | B760: 46231 | C760: 1062949.4 | D760: 0 | E760: =C760-D760 -> 1062949.4 | F760: 68821.017 | G760: =E760/F760 -> 15.445128 | H760: =G760/G759-1 -> -0.0074588117 | I760: =G760/$G$552-1 -> 0.3367166 | J760: 201.8 | K760: =J760/J759-1 -> 0.0026830965 | L760: =J760/$J$552-1 -> 0.086289498
A761: 31 | B761: 46232
A762: 32 | B762: 46233 | E762: =C762-D762 -> 0
A763: 33 | B763: 46234 | E763: =C763-D763 -> 0
A764: 34 | B764: 46235 | E764: =C764-D764 -> 0
A765: 35 | B765: 46236 | E765: =C765-D765 -> 0
A766: 36 | B766: 46237 | E766: =C766-D766 -> 0
A767: 37 | B767: 46238 | E767: =C767-D767 -> 0
A768: 38 | B768: 46239 | E768: =C768-D768 -> 0
A769: 39 | B769: 46240
A770: 40 | B770: 46241
A771: 41 | B771: 46242
A772: 42 | B772: 46243
A773: 43 | B773: 46244
A774: 44 | B774: 46245
A775: 45 | B775: 46246
A776: 46 | B776: 46247
A777: 47 | B777: 46248
A778: 48 | B778: 46249
A779: 49 | B779: 46250
A780: 50 | B780: 46251
... A854: 124 | B854: 46325

Sheet Ledger
B3: ValueDate | C3: GL Description | D3: Debit | E3: Credit | F3: Balance | J3: STOCK | K3: HOLDINGS | L3: AVG. COST
B4: 46023 | C4: Opening Balance | E4: 91880.76 | F4: =E4 -> 91880.76 | J4: TXN | K4: =D359 -> 130 | L4: =E359 -> 297.94615
B5: 46035 | C5: Purchased 95 units of BESI @ €165.13 (USD cost $18,534.54) | D5: -18534.54 | F5: =F4+E5+D5 -> 73346.22 | J5: AVGO | K5: =D284 -> 0 | L5: =E284 -> 0
B6: 20-01-2026 | C6: Purchased 190 units of SMTC @ $75.70 | D6: -14555.72 | F6: =F5+E6+D6 -> 58790.5 | J6: IDEV | K6: =D126 -> 1440 | L6: =E126 -> 83.772201
B7: 22-01-2026 | C7: Sold 232 units of UBER @ $83.51 | E7: 19146.23 | F7: =F6+E7+D7 -> 77936.73 | J7: QQQ | K7: =D132 -> 0 | L7: =E132 -> 0
B8: 22-01-2026 | C8: Sold 160 units of SPMO @ $118.51 | E8: 18737.8 | F8: =F7+E8+D8 -> 96674.53 | J8: MSFT | K8: =D136 -> 22 | L8: =E136 -> 406.20136
B9: 22-01-2026 | C9: Purchased 450 units of INTC @ $54.4 | D9: -24758.39 | F9: =F8+E9+D9 -> 71916.14 | J9: URTH | K9: =D379 -> 1200 | L9: =E379 -> 201.74956
B10: 27-01-2026 | C10: Purchased 75 units of LITE @ $335.2 | D10: -25425.34 | F10: =F9+E10+D10 -> 46490.8 | J10: VOT | K10: =D152 -> 169 | L10: =E152 -> 222.16467
B11: 46050 | C11: Purchased 290 units of VVX @ $68.88 | D11: -20209.87 | F11: =F10+E11+D11 -> 26280.93 | J11: VTV | K11: =D156 -> 185 | L11: =E156 -> 162.20622
B12: 46050 | C12: Purchased 75 units of AVGO @ $338.2 | D12: -25653.06 | F12: =F11+E12+D12 -> 627.87 | J12: IFX | K12: =D369 -> 0 | L12: =G369 -> 0
B13: 46056 | C13: Inflow | E13: 350000 | F13: =F12+E13+D13 -> 350627.87 | J13: WOLF | K13: =D342 -> 600 | L13: =E342 -> 70.856433
B14: 46056 | C14: Purchased 120 units of BE @ $166 | D14: -19940 | F14: =F13+E14+D14 -> 330687.87 | J14: FEZ | K14: =D182 -> 190 | L14: =E182 -> 55.159947
B15: 46056 | C15: Purchased 47 units of AVGO $316 | D15: -14872 | F15: =F14+E15+D15 -> 315815.87 | J15: LITE | K15: =D272 -> 20 | L15: =E272 -> 912
B16: 46056 | C16: Purchased 310 units of INTC @ $48.50 | D16: -15055 | F16: =F15+E16+D16 -> 300760.87 | J16: ON | K16: =240 -> 240 | L16: =E354 -> 101.66667
B17: 46056 | C17: Purchased 84 units of NVDA @ $178 | D17: -14972 | F17: =F16+E17+D17 -> 285788.87 | J17: NVDA | K17: =D147 -> 84 | L17: =E147 -> 139.89131
B18: 46056 | C18: Purchased 70 units of SITM @ $352.90 | D18: -24664.2 | F18: =F17+E18+D18 -> 261124.67 | J18: GOOGL | K18: =D244 -> 0 | L18: =E244 -> 0
B19: 46057 | C19: Purchased 3900 units of KOPN @ $2.55 | D19: -10023 | F19: =F18+E19+D19 -> 251101.67 | J19: JPM | K19: =D229 -> 36 | L19: =E229 -> 280.42528
B20: 46057 | C20: Purchased 110 units of BE @ $139 | D20: -15310 | F20: =F19+E20+D20 -> 235791.67 | J20: SMTC | K20: =D259 -> 0 | L20: =E259 -> 0
B21: 46057 | C21: Purchased 150 units of ONTO @ $199.73 | D21: -30280.76 | F21: =F20+E21+D21 -> 205510.91 | J21: INTC | K21: =D265 -> 0 | L21: =E265 -> 0
B22: 46057 | C22: Purchased 65 units of NVMI @ $444.9677 | D22: -29238.7 | F22: =F21+E22+D22 -> 176272.21 | J22: AMZN | K22: =D234 -> 70 | L22: =E234 -> 215.23829
B23: 46057 | C23: Purchased 35 units of META @ $688.43 | D23: -24370.19 | F23: =F22+E23+D23 -> 151902.02 | J23: DGXX | K23: =D374 -> 3500 | L23: =E374 -> 8.8789714
B24: 46059 | C24: Purchased 850 units of JEPI @ $58.53 | D24: -50167.85 | F24: =F23+E24+D24 -> 101734.17 | J24: BESI | K24: =D255 -> 0 | L24: =E255 -> 0
B25: 46059 | C25: Purchased 4150 units of KOPN @ $2.38 | D25: -9960 | F25: =F24+E25+D25 -> 91774.17 | J25: BOXX | K25: =D349 -> 2430 | L25: =E349 -> 117.33281
B26: 46059 | C26: Purchased 165 units of ZM @ $91.32 | D26: -15087.8 | F26: =F25+E26+D26 -> 76686.37 | J26: WOLF | K26: =D342 -> 600 | L26: =E342 -> 70.856433
B27: 46064 | C27: Purchased 95 units of CIEN @ $283.52 | D27: -27237.72 | F27: =F26+E27+D27 -> 49448.65 | J27: PDFS | K27: =D336 -> 1110 | L27: =E336 -> 44.376577
B28: 46079 | C28: Sold 65 units of NVMI @ $458.35 | E28: 29474.62 | F28: =F27+E28+D28 -> 78923.27 | J28: STM | K28: =D364 -> 0 | L28: =E364 -> 0
B29: 46087 | C29: Purchased 22 units of LITE @ $681.73 | D29: -15181.46 | F29: =F28+E29+D29 -> 63741.81 | J29: 6315.T | K29: =D331 -> 0 | L29: =E331 -> 0
B30: 46087 | C30: Purchased 80 units of NVDA @ $182.34 | D30: -14766.65 | F30: =F29+E30+D30 -> 48975.16 | J30: ZM | K30: =D214 -> 0 | L30: =E214 -> 91.441212
B31: 46093 | C31: Sold 324 units of FOUR @ $46.10 | E31: 14752.98 | F31: =F30+E31+D31 -> 63728.14 | J31: CIEN | K31: =D316 -> 37 | L31: =E316 -> 543.08108
B32: 46093 | C32: Purchased 750 units of SOI @ €56.41 (USD cost $49,550.03) | D32: -49550.03 | F32: =F31+E32+D32 -> 14178.11
B33: 46043 | C33: Purchased 500 units of SKYT @ $34.98 | D33: -17698.49 | F33: =F32+E33+D33 -> -3520.38
B34: 46099 | C34: Sold 500 units of SKYT @ $27.82 | E34: 13737.26 | F34: =F33+E34+D34 -> 10216.88
B35: 46104 | C35: Sold 103 units of WMT @ $120.68 | E35: 12274.59 | F35: =F34+E35+D35 -> 22491.47
B36: 46024 | C36: Received 45.02 Dividend on QQQ | E36: 45.02 | F36: =F35+E36+D36 -> 22536.49
B37: 46028 | C37: Received 16.95 dividend on WMT | E37: 16.95 | F37: =F36+E37+D37 -> 22553.44
B38: 46050 | C38: Received 37.80 dividend for JPM | E38: 37.8 | F38: =F37+E38+D38 -> 22591.24
B39: 46071 | C39: Received 119.95 dividend for BX | E39: 119.95 | F39: =F38+E39+D39 -> 22711.19
B40: 46086 | C40: Received 209.05 of JEPI dividend | E40: 209.05 | F40: =F39+E40+D40 -> 22920.24
B41: 46094 | C41: Received 14.01 of MSFT dividend | E41: 14.01 | F41: =F40+E41+D41 -> 22934.25
B42: 46098 | C42: Received 10 of AAPL dividend | E42: 10 | F42: =F41+E42+D42 -> 22944.25
B43: 46107 | C43: Received 12.17 of FEZ dividend | E43: 12.17 | F43: =F42+E43+D43 -> 22956.42
B44: 46108 | C44: Received 28.67 of META dividend | E44: 28.67 | F44: =F43+E44+D44 -> 22985.09
B45: 46111 | C45: Received 41.55 of QQQ dividend | E45: 41.55 | F45: =F44+E45+D45 -> 23026.64
... B47: 46140 | C47: Sold 115 units of BX @ 121.48 | E47: 13797.29 | F47: =F46+E47+D47 -> 85120.92
B48: 46140 | C48: Sold 290 units of VVX @ $63.29 | E48: 18252.35 | F48: =F47+E48+D48 -> 103373.27 | H48: =176418-70000 -> 106418
B49: 46142 | C49: Purchased 1450 units of 6315.T @ ¥2952.06 | D49: -27139.75 | F49: =F48+E49+D49 -> 76233.52
B50: 46142 | C50: Sold 8050 units of KOPN @ $3.71 | E50: 29706.3 | F50: =F49+E50+D50 -> 105939.82
B51: 46142 | C51: Sold 70 units of SITM @530.40 | E51: 37209.43 | F51: =F50+E51+D51 -> 143149.25 | J51: Date | K51: Stock | L51: Units Disposed | M51: Purchase Cost | N51: Sales Proceeds | O51: Net Gain(loss) | P51: Net Gain/Loss (%) | Q51: Comment
B52: 46142 | C52: Sold 230 units of BE @ 267 | E52: 61631 | F52: =F51+E52+D52 -> 204780.25 | J52: 22-01-2026 | K52: UBER | L52: 232 | M52: =-F201 -> 19614.11 | N52: =E7 -> 19146.23 | O52: =N52-M52 -> -467.88 | P52: =O52/M52 -> -0.023854256
B53: 46142 | C53: Sold 310 units of INTC @ 92.20 | E53: 28575.36 | F53: =F52+E53+D53 -> 233355.61 | J53: 22-01-2026 | K53: SPMO | L53: 160 | M53: =-F161 -> 19808.46 | N53: =E8 -> 18737.8 | O53: =N53-M53 -> -1070.66 | P53: =O53/M53 -> -0.054050643
B54: 46142 | C54: Sold 47 units of AVGO @ 411.00 | E54: 19296.6 | F54: =F53+E54+D54 -> 252652.21 | J54: 26-02-2026 | K54: NVMI | L54: 65 | M54: =-D22 -> 29238.7 | N54: =E28 -> 29474.62 | O54: =N54-M54 -> 235.92 | P54: =O54/M54 -> 0.0080687582
B55: 46143 | C55: Purchased 800 units of PDFS @ $42.95 | D55: -34400 | F55: =F54+E55+D55 -> 218252.21 | J55: 46093 | K55: FOUR | L55: 324 | M55: =-SUM(F166:F169) -> 32338.61 | N55: =E31 -> 14752.98 | O55: =N55-M55 -> -17585.63 | P55: =O55/M55 -> -0.54379672
B56: 46143 | C56: Purchased 1000 units of WOLF @ $30.90 | D56: -30940 | F56: =F55+E56+D56 -> 187312.21 | J56: 46099 | K56: SKYT | L56: 500 | M56: =-D33 -> 17698.49 | N56: =E34 -> 13737.26 | O56: =N56-M56 -> -3961.23 | P56: =O56/M56 -> -0.2238174
B57: 46143 | C57: Purchased 600 units of BOXX @ $116.58 | D57: -69985 | F57: =F56+E57+D57 -> 117327.21 | J57: 46104 | K57: WMT | L57: 103 | M57: =-F217 -> 9804.08 | N57: =E35 -> 12274.59 | O57: =N57-M57 -> 2470.51 | P57: =O57/M57 -> 0.25198795
B58: 46147 | C58: Sold 1000 units of WOLF @ $39.25 | E58: 39229.15 | F58: =F57+E58+D58 -> 156556.36 | J58: 46134 | K58: JEPI | L58: 850 | M58: =-F174 -> 50167.8 | N58: =E46 -> 48296.99 | O58: =N58-M58 -> -1870.81 | P58: =O58/M58 -> -0.037291051
B59: 46149 | C59: Sold 750 units of SOI @ €153.2776 (USD proceeds $134,493.24) | D59: 134493.24 | F59: =F58+E59+D59 -> 291049.6 | J59: 46141 | K59: BX | L59: 115 | M59: =-F248 -> 20142.16 | N59: =F249 -> 13797.29 | O59: =N59-M59 -> -6344.87 | P59: =O59/M59 -> -0.31500445
B60: 46149 | C60: Sold 450 units of INTC @ $110.96 | D60: 49513.61 | F60: =F59+E60+D60 -> 340563.21 | J60: 46141 | K60: VVX | L60: 290 | M60: =-F275 -> 20209.87 | N60: =F276 -> 18252.35 | O60: =N60-M60 -> -1957.52 | P60: =O60/M60 -> -0.096859604
B61: 46149 | C61: Sold 150 units of ONTO @ $293.68 | D61: 43661.78 | F61: =F60+E61+D61 -> 384224.99 | J61: 46142 | K61: KOPN | L61: 8050 | M61: =-SUM(F297:F298) -> 19983 | N61: =E50 -> 29706.3 | O61: =N61-M61 -> 9723.3 | P61: =O61/M61 -> 0.48657859
B62: 46149 | C62: Sold 95 units of CIEN @ $566.06 | D62: 53336.68 | F62: =F61+E62+D62 -> 437561.67 | J62: 46142 | K62: SITM | L62: 70 | M62: =-F292 -> 24664 | N62: =F293 -> 37209.43 | O62: =N62-M62 -> 12545.43 | P62: =O62/M62 -> 0.5086535
B63: 46149 | C63: Sold 97 units of LITE @ $913.05 | D63: 88004.69 | F63: =F62+E63+D63 -> 525566.36 | J63: 46142 | K63: BE | L63: 230 | M63: =-SUM(F286:F287) -> 35250 | N63: =F288 -> 61631 | O63: =N63-M63 -> 26381 | P63: =O63/M63 -> 0.74839716
B64: 46149 | C64: Purchased 240 units of ON @ $101.50 | E64: -24400 | F64: =F63+E64+D64 -> 501166.36 | J64: 46142 | K64: INTC | L64: 310 | M64: =-F262 -> 15055 | N64: =E53 -> 28575.36 | O64: =N64-M64 -> 13520.36 | P64: =O64/M64 -> 0.89806443
B65: 46150 | C65: Purchased 20 units of LITE @ $910 | E65: -18240 | F65: =F64+E65+D65 -> 482926.36 | J65: 46142 | K65: AVGO | L65: 47 | M65: =-F281 -> 14872 | N65: =E54 -> 19296.6 | O65: =N65-M65 -> 4424.6 | P65: =O65/M65 -> 0.2975121
B66: 46150 | C66: Purchased 37 units of CIEN @ $542 | E66: -20094 | F66: =F65+E66+D66 -> 462832.36 | J66: 46147 | K66: WOLF | L66: 1000 | M66: =-D56 -> 30940 | N66: =E58 -> 39229.15 | O66: =N66-M66 -> 8289.15 | P66: =O66/M66 -> 0.26791047
B67: 46150 | C67: Purchased 310 units of PDFS @ $47.80 | E67: -14858 | F67: =F66+E67+D67 -> 447974.36 | J67: 46149 | K67: SOI | L67: 750 | M67: =-D32 -> 49550.03 | N67: =D59 -> 134493.24 | O67: =N67-M67 -> 84943.21 | P67: =O67/M67 -> 1.7142918
B68: 46153 | C68: Sold 600 units of BOXX @ $116.65 | D68: 69971.55 | F68: =F67+E68+D68 -> 517945.91 | J68: 46149 | K68: INTC | L68: 450 | M68: =-F261 -> 24758.39 | N68: =D60 -> 49513.61 | O68: =N68-M68 -> 24755.22 | P68: =O68/M68 -> 0.99987196
B69: 46153 | C69: Purchased 100 units of TXN @ $295.49 | E69: -29569 | F69: =F68+E69+D69 -> 488376.91 | J69: 46149 | K69: ONTO | L69: 150 | M69: =-D21 -> 30280.76 | N69: =D61 -> 43661.78 | O69: =N69-M69 -> 13381.02 | P69: =O69/M69 -> 0.44189842
B70: 46153 | C70: Purchased 500 units of STM @ $59.05 | E70: -29545 | F70: =F69+E70+D70 -> 458831.91 | J70: 46149 | K70: CIEN | L70: 95 | M70: =-D27 -> 27237.72 | N70: =D62 -> 53336.68 | O70: =N70-M70 -> 26098.96 | P70: =O70/M70 -> 0.9581918
B71: 46153 | C71: Purchased 2000 units of BOXX @ $116.718 | E71: -234505.77 | F71: =F70+E71+D71 -> 224326.14 | J71: 46149 | K71: LITE | L71: 97 | M71: =-SUM(F268:F269) -> 40606.8 | N71: =D63 -> 88004.69 | O71: =N71-M71 -> 47397.89 | P71: =O71/M71 -> 1.1672402
B72: 46155 | C72: Purchased 600 units of IFX @ €61.86 (USD Cost is $43,852.65) | E72: -43852.65 | F72: =F71+E72+D72 -> 180473.49 | J72: 46153 | K72: BOXX | L72: 600 | M72: =-D57 -> 69985 | N72: =D68 -> 69971.55 | O72: =N72-M72 -> -13.45 | P72: =O72/M72 -> -0.00019218404
B73: 46155 | C73: Purchased 30 units of TXN @ $304.80 | E73: -9164 | F73: =F72+E73+D73 -> 171309.49 | J73: 46163 | K73: ZM | L73: 165 | M73: =-F212 -> 15087.8 | N73: =E77 -> 15839.47 | O73: =N73-M73 -> 751.67 | P73: =O73/M73 -> 0.049819722
B74: 46155 | C74: Purchased 430 units of BOXX @ $116.73 | E74: -50612.97 | F74: =F73+E74+D74 -> 120696.52 | J74: 46164 | K74: META | L74: 78 | M74: =-SUM(F193:F195) -> 53239.17 | N74: =E78 -> 46979.39 | O74: =N74-M74 -> -6259.78 | P74: =O74/M74 -> -0.11757847
B75: 46155 | C75: Purchased 3500 units of DGXX @ C$11.99 | E75: -31076.4 | F75: =F74+E75+D75 -> 89620.12 | J75: 46196 | K75: IFX | L75: 600 | M75: =-F367 -> 43852.65 | N75: =F368 -> 55751.11 | O75: =N75-M75 -> 11898.46 | P75: =O75/M75 -> 0.27132819
B76: 46155 | C76: Purchased 600 units of WOLF @ $70.22 | E76: -42513.86 | F76: =F75+E76+D76 -> 47106.26 | J76: 46196 | K76: BESI | L76: 95 | M76: =-F253 -> 18534.54 | N76: =F254 -> 32377.83 | O76: =N76-M76 -> 13843.29 | P76: =O76/M76 -> 0.74689148
B77: 46163 | C77: Sold 165 units of ZM @ $96.12 | E77: 15839.47 | F77: =F76+E77+D77 -> 62945.73 | J77: 46196 | K77: SMTC | L77: 190 | M77: =-F257 -> 14555.72 | N77: =F258 -> 30296.67 | O77: =N77-M77 -> 15740.95 | P77: =O77/M77 -> 1.0814271
B78: 46164 | C78: Sold 78 units of META @ $607.485428 | E78: 46979.39 | F78: =F77+E78+D78 -> 109925.12 | J78: 46196 | K78: AVGO | L78: 75 | M78: =-F280 -> 25653.06 | N78: =F283 -> 28014.35 | O78: =N78-M78 -> 2361.29 | P78: =O78/M78 -> 0.092047109
B79: 46196 | C79: Sold 600 units of IFX @ €81.6209 (USD proceeds $55,751.11) | D79: 55751.11 | F79: =F78+E79+D79 -> 165676.23 | J79: 46197 | K79: TOWA | L79: 1450 | M79: =-F329 -> 27139.75 | N79: =F330 -> 28382.79 | O79: =N79-M79 -> 1243.04 | P79: =O79/M79 -> 0.045801454
B80: 46196 | C80: Sold 95 units of BESI @ €300.046316 (USD proceeds $32,377.83) | D80: 32377.83 | F80: =F79+E80+D80 -> 198054.06 | J80: =B131 -> 46202 | K80: QQQ | L80: =-D131 -> 81 | M80: =-F130 -> 35809.96 | N80: =F131 -> 57478.07 | O80: =N80-M80 -> 21668.11 | P80: =O80/M80 -> 0.60508613
B81: 46196 | C81: Sold 190 units of SMTC @ $161.133942 (USD proceeds $30,296.67) | D81: 30296.67 | F81: =F80+E81+D81 -> 228350.73 | J81: =B243 -> 46202 | K81: GOOGL | L81: =-D243 -> 68 | M81: =-F242 -> 12009.11 | N81: =F243 -> 23008.06 | O81: =N81-M81 -> 10998.95 | P81: =O81/M81 -> 0.91588386
B82: 46196 | C82: Sold 75 units of AVGO @ $377.622084 (USD proceeds $28,014.35) | D82: 28014.35 | F82: =F81+E82+D82 -> 256365.08 | J82: =B146 -> 46202 | K82: NVDA | L82: =-D146 -> 146 | M82: =-D146*((-SUM(F143:F145))/SUM(D143:D145)) -> 25326.423 | N82: =F146 -> 28146.92 | O82: =N82-M82 -> 2820.4968 | P82: =O82/M82 -> 0.11136578
B83: 46197 | C83: Sold 1,450 units of TOWA @ JPY3,221.01931 (settlement proceeds $28,382.79) | D83: 28382.79 | F83: =F82+E83+D83 -> 284747.87
B84: 46199 | C84: Sold 500 units of STM @ $71.39 (USD proceeds $35,674.26) | D84: 35674.26 | F84: =F83+E84+D84 -> 320422.13
B85: 46202 | C85: Sold 81 units of QQQ @ $715.127483 (USD proceeds $57,478.07) | D85: 57478.07 | F85: =F84+E85+D85 -> 377900.2
B86: 46202 | C86: Sold 68 units of GOOGL @ $342.262356 (USD proceeds $23,008.06) | D86: 23008.06 | F86: =F85+E86+D86 -> 400908.26
B87: 46202 | C87: Sold 146 units of NVDA @ $194.893243 (USD proceeds $28,146.92) | D87: 28146.92 | F87: =F86+E87+D87 -> 429055.18
B88: 46113 | C88: Received 34.13 dividend on AVGO | E88: 34.13 | F88: =F87+E88+D88 -> 429089.31
B89: 46113 | C89: Received 60.30 dividend on VOT | E89: 60.3 | F89: =F88+E89+D89 -> 429149.61
B90: 46113 | C90: Received 139.76 dividend on VTV | E90: 139.76 | F90: =F89+E90+D90 -> 429289.37
B91: 46114 | C91: Received 1.02 dividend on NVDA | E91: 1.02 | F91: =F90+E91+D91 -> 429290.39
B92: 46119 | C92: Received 250.20 dividend on JEPI | E92: 250.2 | F92: =F91+E92+D92 -> 429540.59
B93: 46119 | C93: Received 17.85 dividend on WMT | E93: 17.85 | F93: =F92+E93+D93 -> 429558.44 | K93: Total | M93: =SUM(M52:M91) -> 873413.16 | N93: =SUM(N52:N91) -> 1189374.2 | O93: =SUM(O52:O91) -> 315961 | P93: =O93/M93 -> 0.36175433
B94: 46143 | C94: Received 37.80 dividend on JPM | E94: 37.8 | F94: =F93+E94+D94 -> 429596.24
B95: 46146 | C95: Received 149.21 dividend on BESI | E95: 149.21 | F95: =F94+E95+D95 -> 429745.45
B96: 46185 | C96: Received 14.01 dividend on MSFT | E96: 14.01 | F96: =F95+E96+D96 -> 429759.46
B97: 46189 | C97: Received 10.47 dividend on GOOGL | E97: 10.47 | F97: =F96+E97+D97 -> 429769.93
B98: 46191 | C98: Received 319.86 dividend on IDEV | E98: 319.86 | F98: =F97+E98+D98 -> 430089.79
B99: 46198 | C99: Received 147.85 dividend on FEZ | E99: 147.85 | F99: =F98+E99+D99 -> 430237.64
B100: 46202 | C100: Received 25.55 dividend on NVDA | E100: 25.55 | F100: =F99+E100+D100 -> 430263.19
B101: 46227 | C101: Purchased 1200 units of URTH @ $200.840367 | D101: -242099.47 | F101: =F100+E101+D101 -> 188163.72
B102: 46227 | C102: Purchased 1100 units of IDEV @ $88.344155 | D102: -97766.19 | F102: =F101+E102+D102 -> 90397.53
F117: =F102 -> 90397.53
...

Sheet StoneX Ledger
A1: STONEX LEDGER
B3: Date | C3: Description | D3: Debit | E3: Credit | F3: Balance | H3: STOCK | I3: HOLDINGS | J3: AVG. COST
C4: Opening Balance | E4: 150000 | F4: =E4 -> 150000 | H4: NVDA | I4: 84 | J4: 178
B5: 46056 | C5: Purchased 120 units of BE @ $166.00 (USD cost $19,940.00) | D5: -19940 | F5: =F4+E5+D5 -> 130060 | H5: ZM | I5: 0 | J5: 91.32
B6: 46056 | C6: Purchased 47 units of AVGO @ $316.00 (USD cost $14,872.00) | D6: -14872 | F6: =F5+E6+D6 -> 115188 | H6: PDFS | I6: 1110 | J6: =(34380+14858)/1110 -> 44.358559
B7: 46056 | C7: Purchased 310 units of INTC @ $48.50 (USD cost $15,055.00) | D7: -15055 | F7: =F6+E7+D7 -> 100133 | H7: TXN | I7: 130 | J7: =(29569+9164)/130 -> 297.94615
B8: 46056 | C8: Purchased 84 units of NVDA @ $178.00 (USD cost $14,972.00) | D8: -14972 | F8: =F7+E8+D8 -> 85161 | H8: ON | I8: 240 | J8: 101.66667
B9: 46056 | C9: Purchased 70 units of SITM @ $352.06 (USD cost $24,664.20) | D9: -24664.2 | F9: =F8+E9+D9 -> 60496.8 | H9: LITE | I9: 20 | J9: 912
B10: 46057 | C10: Purchased 3,900 units of KOPN @ $2.55 (USD cost $10,023.00) | D10: -10023 | F10: =F9+E10+D10 -> 50473.8 | H10: CIEN | I10: 37 | J10: 543.08108
B11: 46057 | C11: Purchased 110 units of BE @ $139.00 (USD cost $15,310.00) | D11: -15310 | F11: =F10+E11+D11 -> 35163.8 | H11: STM | I11: 0 | J11: 59.09
B12: 46059 | C12: Purchased 4,150 units of KOPN @ $2.38 (USD cost $9,960.00) | D12: -9960 | F12: =F11+E12+D12 -> 25203.8
B13: 46059 | C13: Purchased 165 units of ZM @ $91.32 (USD cost $15,087.80) | D13: -15087.8 | F13: =F12+E13+D13 -> 10116
B14: 46142 | C14: Sold 8,050 units of KOPN @ $3.71 (USD proceeds $29,706.30) | E14: 29706.3 | F14: =F13+E14+D14 -> 39822.3
B15: 46142 | C15: Sold 70 units of SITM @ $531.86 (USD proceeds $37,209.43) | E15: 37209.43 | F15: =F14+E15+D15 -> 77031.73
B16: 46142 | C16: Sold 230 units of BE @ $268.05 (USD proceeds $61,631.23) | E16: 61631.23 | F16: =F15+E16+D16 -> 138662.96
B17: 46142 | C17: Sold 310 units of INTC @ $92.25 (USD proceeds $28,575.36) | E17: 28575.36 | F17: =F16+E17+D17 -> 167238.32
B18: 46142 | C18: Sold 47 units of AVGO @ $411.00 (USD proceeds $19,296.60) | E18: 19296.6 | F18: =F17+E18+D18 -> 186534.92
B19: 46143 | C19: Purchased 800 units of PDFS @ $42.95 (USD cost $34,380.00) | D19: -34380 | F19: =F18+E19+D19 -> 152154.92
B20: 46143 | C20: Purchased 1,000 units of WOLF @ $30.90 (USD cost $30,920.00) | D20: -30920 | F20: =F19+E20+D20 -> 121234.92
B21: 46143 | C21: Purchased 600 units of BOXX @ $116.58 (USD cost $69,965.00) | D21: -69965 | F21: =F20+E21+D21 -> 51269.92
B22: 46147 | C22: Sold 1,000 units of WOLF @ $39.25 (USD proceeds $39,229.15) | E22: 39229.15 | F22: =F21+E22+D22 -> 90499.07
B23: 46149 | C23: Purchased 240 units of ON @ $101.67 (USD cost $24,400.00) | D23: -24400 | F23: =F22+E23+D23 -> 66099.07
B24: 46150 | C24: Purchased 20 units of LITE @ $910.00 (USD cost $18,240.00) | D24: -18240 | F24: =F23+E24+D24 -> 47859.07
B25: 46150 | C25: Purchased 37 units of CIEN @ $542.00 (USD cost $20,094.00) | D25: -20094 | F25: =F24+E25+D25 -> 27765.07
B26: 46150 | C26: Purchased 310 units of PDFS @ $47.80 (USD cost $14,858.00) | D26: -14858 | F26: =F25+E26+D26 -> 12907.07
B27: 46153 | C27: Sold 600 units of BOXX @ $116.65 (USD proceeds $69,971.55) | E27: 69971.55 | F27: =F26+E27+D27 -> 82878.62
B28: 46153 | C28: Purchased 100 units of TXN @ $295.49 (USD cost $29,569.00) | D28: -29569 | F28: =F27+E28+D28 -> 53309.62
B29: 46153 | C29: Purchased 500 units of STM @ $59.05 (USD cost $29,545.00) | D29: -29545 | F29: =F28+E29+D29 -> 23764.62
B30: 46155 | C30: Purchased 30 units of TXN @ $304.80 (USD cost $9,164.00) | D30: -9164 | F30: =F29+E30+D30 -> 14600.62
B31: 46163 | C31: Sold 165 units of ZM @ $96.12 (USD proceeds $15,839.47) | E31: 15839.47 | F31: =F30+E31+D31 -> 30440.09
B32: 46199 | C32: Sold 500 units of STM @ $71.39 (USD proceeds $35,674.26) | E32: 35674.26 | F32: =F31+E32+D32 -> 66114.35
B33: RETURNS SUMMARY
B35: UNREALIZED P&L (Open Positions) | C35: Shares | D35: Avg. Cost | E35: Cost Basis | F35: Mkt Price | G35: Mkt Value | H35: Unrealized P&L | I35: Return %
B36: NVDA | C36: 84 | D36: 178 | E36: 14972 | F36: ='Portfolio Snapshot'!B6 -> 218.99 | G36: =C36*F36 -> 18395.16 | H36: =G36-E36 -> 3423.16 | I36: =H36/E36 -> 0.22863746
B37: ZM | C37: 0 | D37: 91.441212 | E37: 0 | F37: 0 | G37: 0 | H37: 0 | I37: 0
B38: PDFS | C38: 1110 | D38: =(34380+14858)/1110 -> 44.358559 | E38: =C38*D38 -> 49238 | F38: ='Portfolio Snapshot'!B12 -> 45.9 | G38: =C38*F38 -> 50949 | H38: =G38-E38 -> 1711 | I38: =H38/E38 -> 0.034749584
B39: TXN | C39: 130 | D39: =(29569+9164)/130 -> 297.94615 | E39: =C39*D39 -> 38733 | F39: ='Portfolio Snapshot'!B14 -> 278.4 | G39: =C39*F39 -> 36192 | H39: =G39-E39 -> -2541 | I39: =H39/E39 -> -0.065602974
B40: ON | C40: 240 | D40: 101.66667 | E40: 24400 | F40: ='Portfolio Snapshot'!B13 -> 78.33 | G40: =C40*F40 -> 18799.2 | H40: =G40-E40 -> -5600.8 | I40: =H40/E40 -> -0.22954098
B41: LITE | C41: 20 | D41: 912 | E41: 18240 | F41: ='Portfolio Snapshot'!B10 -> 838.06 | G41: =C41*F41 -> 16761.2 | H41: =G41-E41 -> -1478.8 | I41: =H41/E41 -> -0.081074561
B42: CIEN | C42: 37 | D42: 543.08108 | E42: 20094 | F42: ='Portfolio Snapshot'!B11 -> 403.76 | G42: =C42*F42 -> 14939.12 | H42: =G42-E42 -> -5154.88 | I42: =H42/E42 -> -0.25653827
B43: STM | C43: 0 | D43: 59.09 | E43: 0 | F43: =IFERROR(_xlfn.XLOOKUP(B43,'Portfolio Snapshot'!$A$2:$A$18,'Portfolio Snapshot'!$B$2:$B$18),0) -> 0 | G43: =C43*F43 -> 0 | H43: =G43-E43 -> 0 | I43: =IF(E43=0,0,H43/E43) -> 0
B44: Total Unrealized | E44: =SUM(E36:E43) -> 165677 | G44: =SUM(G36:G43) -> 156035.68 | H44: =SUM(H36:H43) -> -9641.32 | I44: =IF(E44=0,0,H44/E44) -> -0.058193473
B47: REALIZED P&L (Closed Positions) | C47: Shares | D47: Buy Avg | E47: Cost Basis | F47: Sell Avg | G47: Proceeds | H47: Realized P&L | I47: Return %
B48: KOPN | C48: 8050 | D48: 2.48 | E48: 19983 | F48: 3.71 | G48: 29706.3 | H48: =G48-E48 -> 9723.3 | I48: =H48/E48 -> 0.48657859
B49: SITM | C49: 70 | D49: 352.06 | E49: 24664.2 | F49: 531.86 | G49: 37209.43 | H49: =G49-E49 -> 12545.23 | I49: =H49/E49 -> 0.50864127
B50: BE | C50: 230 | D50: 153.26 | E50: 35250 | F50: 268.05 | G50: 61631.23 | H50: =G50-E50 -> 26381.23 | I50: =H50/E50 -> 0.74840369
B51: INTC | C51: 310 | D51: 48.5 | E51: 15055 | F51: 92.25 | G51: 28575.36 | H51: =G51-E51 -> 13520.36 | I51: =H51/E51 -> 0.89806443
B52: AVGO | C52: 47 | D52: 316 | E52: 14872 | F52: 411 | G52: 19296.6 | H52: =G52-E52 -> 4424.6 | I52: =H52/E52 -> 0.2975121
B53: WOLF | C53: 1000 | D53: 30.92 | E53: 30920 | F53: 39.22915 | G53: 39229.15 | H53: =G53-E53 -> 8309.15 | I53: =H53/E53 -> 0.2687306
B54: BOXX | C54: 600 | D54: 116.58 | E54: 69965 | F54: 116.65 | G54: 69971.55 | H54: =G54-E54 -> 6.55 | I54: =H54/E54 -> 9.3618238e-05
B55: ZM | C55: 165 | D55: 91.441212 | E55: 15087.8 | F55: 96.12 | G55: 15839.47 | H55: =G55-E55 -> 751.67 | I55: =H55/E55 -> 0.049819722
B56: STM | C56: 500 | D56: 59.09 | E56: 29545 | F56: 71.39 | G56: 35674.26 | H56: =G56-E56 -> 6129.26 | I56: =H56/E56 -> 0.20745507
B57: Total Realized | E57: =SUM(E48:E56) -> 255342 | G57: =SUM(G48:G56) -> 337133.35 | H57: =SUM(H48:H56) -> 81791.35 | I57: =IF(E57=0,0,H57/E57) -> 0.32032079
B58: ACCOUNT SUMMARY
B60: Opening Capital | C60: =E4 -> 150000
B61: Cash Balance | C61: =F32 -> 66114.35
B62: Portfolio Mkt Value | C62: =G44 -> 156035.68
B63: Total Account Value | C63: =C61+C62 -> 222150.03
B65: Total P&L (Realized + Unrealized) | C65: =H57+H44 -> 72150.03
B66: Total Return on Capital | C66: =(C63-C60)/C60 -> 0.4810002

Sheet Subscription
A1: Date | B1: Client's Name | C1: Dollar inflow (outflow) | D1: Nav on Sub Date | E1: Total Unit Purchased | F1: Balance Units
A2: 45453 | B2: OG | C2: 300000 | D2: 10 | E2: =C2/D2 -> 30000 | F2: =E2 -> 30000
A3: 45691 | B3: OG | C3: =9157*D3 -> 99994.44 | D3: 10.92 | E3: =C3/D3 -> 9157 | F3: =E3+F2 -> 39157
A4: 46056 | B4: OG | C4: 350000 | D4: 11.8 | E4: =C4/D4 -> 29661.017 | F4: =E4+F3 -> 68818.017
C10: =SUM(C2:C9) -> 749994.44 | D10: =C10/E10 -> 10.898228 | E10: =SUM(E2:E9) -> 68818.017

Sheet Portfolio Allocation
A1: Securities | B1: TICKER | C1: Status | D1: Strategic Allocation | E1: Current Allocation | F1: Strategic Dollar Allocation ($) | G1: Current Dollar Allocation | H1: Dollar Difference | I1: Difference | J1: Daily Change | K1: Total Return
A2: Core | D2: =D16+D12 -> 0.6 | J2: =IFERROR(VLOOKUP(B2,'Daily Change'!A:F,5,FALSE),"")
A3: Market/Large Cap | J3: =IFERROR(VLOOKUP(B3,'Daily Change'!A:F,5,FALSE),"") | K3: =IFERROR(VLOOKUP(B3,'Portfolio Snapshot'!$A:$L,12,),"")
A4: Developed Economies (ex US) | B4: IDEV | C4: {=_xlfn.IFS(I4>0,"Underweight",I4=0,"",I4<0,"Overweight")} -> Overweight | D4: 0.07 | E4: =G4/$G$47 -> 0.1771776 | F4: =D4*$F$46 -> 52499.611 | G4: =IFERROR(VLOOKUP(B:B,'Portfolio Snapshot'!$A:$L,4,0),0) -> 132883.2 | H4: =F4-G4 -> -80383.589 | I4: =D4-E4 -> -0.1071776 | J4: =IFERROR(VLOOKUP(B4,'Daily Change'!A:F,5,FALSE),"") -> 0 | K4: =IFERROR(VLOOKUP(B4,'Portfolio Snapshot'!$A:$L,12,),"") -> 0.1052609
A5: US Large Cap value | B5: VTV | C5: {=_xlfn.IFS(I5>0,"Underweight",I5=0,"",I5<0,"Overweight")} -> Underweight | D5: 0.07 | E5: =G5/$G$47 -> 0.055097933 | F5: =D5*$F$46 -> 52499.611 | G5: =IFERROR(VLOOKUP(B:B,'Portfolio Snapshot'!$A:$L,4,0),0) -> 41323.45 | H5: =F5-G5 -> 11176.161 | I5: =D5-E5 -> 0.014902067 | J5: =IFERROR(VLOOKUP(B5,'Daily Change'!A:F,5,FALSE),"") -> -0.0027679807 | K5: =IFERROR(VLOOKUP(B5,'Portfolio Snapshot'!$A:$L,12,),"") -> 0.38144604
A6: Microsoft | B6: MSFT | C6: {=_xlfn.IFS(I6>0,"Underweight",I6=0,"",I6<0,"Overweight")} -> Underweight | D6: 0.06 | E6: =G6/$G$47 -> 0.01466256 | F6: =D6*$F$46 -> 44999.666 | G6: =IFERROR(VLOOKUP(B:B,'Portfolio Snapshot'!$A:$L,4,0),0) -> 10996.92 | H6: =F6-G6 -> 34002.746 | I6: =D6-E6 -> 0.04533744 | J6: =IFERROR(VLOOKUP(B6,'Daily Change'!A:F,5,FALSE),"") -> 0.025437985 | K6: =IFERROR(VLOOKUP(B6,'Portfolio Snapshot'!$A:$L,12,),"") -> 0.2318644
A7: Alphabet Inc | B7: GOOGL | C7: {=_xlfn.IFS(I7>0,"Underweight",I7=0,"",I7<0,"Overweight")} -> Underweight | D7: 0.06 | E7: =G7/$G$47 -> 0 | F7: =D7*$F$46 -> 44999.666 | G7: =IFERROR(VLOOKUP(B:B,'Portfolio Snapshot'!$A:$L,4,0),0) -> 0 | H7: =F7-G7 -> 44999.666 | I7: =D7-E7 -> 0.06 | J7: =IFERROR(VLOOKUP(B7,'Daily Change'!A:F,5,FALSE),"") -> -0.012912838 | K7: =IFERROR(VLOOKUP(B7,'Portfolio Snapshot'!$A:$L,12,),"")
A8: NASDAQ100 | B8: QQQ | C8: {=_xlfn.IFS(I8>0,"Underweight",I8=0,"",I8<0,"Overweight")} -> Underweight | D8: 0.07 | E8: =G8/$G$47 -> 0 | F8: =D8*$F$46 -> 52499.611 | G8: =IFERROR(VLOOKUP(B:B,'Portfolio Snapshot'!$A:$L,4,0),0) -> 0 | H8: =F8-G8 -> 52499.611 | I8: =D8-E8 -> 0.07 | J8: =IFERROR(VLOOKUP(B8,'Daily Change'!A:F,5,FALSE),"") -> -0.0036944096 | K8: =IFERROR(VLOOKUP(B8,'Portfolio Snapshot'!$A:$L,12,),"")
A9: Europe | B9: FEZ | C9: {=_xlfn.IFS(I9>0,"Underweight",I9=0,"",I9<0,"Overweight")} -> Underweight | D9: 0.07 | E9: =G9/$G$47 -> 0.0180424 | F9: =D9*$F$46 -> 52499.611 | G9: =IFERROR(VLOOKUP(B:B,'Portfolio Snapshot'!$A:$L,4,0),0) -> 13531.8 | H9: =F9-G9 -> 38967.811 | I9: =D9-E9 -> 0.0519576 | J9: =IFERROR(VLOOKUP(B9,'Daily Change'!A:F,5,FALSE),"") -> 0 | K9: =IFERROR(VLOOKUP(B9,'Portfolio Snapshot'!$A:$L,12,),"") -> 0.29115424
A10: Nvidia Corp | B10: NVDA | C10: {=_xlfn.IFS(I10>0,"Underweight",I10=0,"",I10<0,"Overweight")} -> Underweight | D10: 0.06 | E10: =G10/$G$47 -> 0.02452688 | F10: =D10*$F$46 -> 44999.666 | G10: =IFERROR(VLOOKUP(B:B,'Portfolio Snapshot'!$A:$L,4,0),0) -> 18395.16 | H10: =F10-G10 -> 26604.506 | I10: =D10-E10 -> 0.03547312 | J10: =IFERROR(VLOOKUP(B10,'Daily Change'!A:F,5,FALSE),"") -> -0.0010491743 | K10: =IFERROR(VLOOKUP(B10,'Portfolio Snapshot'!$A:$L,12,),"") -> 0.56557855
A11: Meta Platforms Inc | B11: META | C11: {=_xlfn.IFS(I11>0,"Underweight",I11=0,"",I11<0,"Overweight")} -> Underweight | D11: 0.06 | E11: =G11/$G$47 -> 0 | F11: =D11*$F$46 -> 44999.666 | G11: =IFERROR(VLOOKUP(B:B,'Portfolio Snapshot'!$A:$L,4,0),0) -> 0 | H11: =F11-G11 -> 44999.666 | I11: =D11-E11 -> 0.06 | J11: =IFERROR(VLOOKUP(B11,'Daily Change'!A:F,5,FALSE),"") -> 0.0019192554 | K11: =IFERROR(VLOOKUP(B11,'Portfolio Snapshot'!$A:$L,12,),"")
C12: {=_xlfn.IFS(I12>0,"Underweight",I12=0,"",I12<0,"Overweight")} -> Underweight | D12: =SUM(D4:D10) -> 0.46 | E12: =SUM(E4:E10) -> 0.28950737 | F12: =SUM(F4:F10) -> 344997.44 | G12: =SUM(G4:G10) -> 217130.53 | H12: =F12-G12 -> 127866.91 | I12: =D12-E12 -> 0.17049263 | J12: =IFERROR(VLOOKUP(B12,'Daily Change'!A:F,5,FALSE),"") | K12: =IFERROR(VLOOKUP(B12,'Portfolio Snapshot'!$A:$L,12,),"")
A13: Small-Mid Cap | J13: =IFERROR(VLOOKUP(B13,'Daily Change'!A:F,5,FALSE),"") | K13: =IFERROR(VLOOKUP(B13,'Portfolio Snapshot'!$A:$L,12,),"")
A14: Value/Quality | B14: VBR | C14: {=_xlfn.IFS(I14>0,"Underweight",I14=0,"",I14<0,"Overweight")} -> Underweight | D14: 0.07 | E14: =G14/$G$47 -> 0 | F14: =D14*$F$46 -> 52499.611 | G14: =IFERROR(VLOOKUP(B:B,'Portfolio Snapshot'!$A:$L,4,0),0) -> 0 | H14: =F14-G14 -> 52499.611 | I14: =D14-E14 -> 0.07 | J14: =IFERROR(VLOOKUP(B14,'Daily Change'!A:F,5,FALSE),"") -> 0 | K14: =IFERROR(VLOOKUP(B14,'Portfolio Snapshot'!$A:$L,12,),"")
A15: Growth | B15: VOT | C15: {=_xlfn.IFS(I15>0,"Underweight",I15=0,"",I15<0,"Overweight")} -> Underweight | D15: 0.07 | E15: =G15/$G$47 -> 0.068057427 | F15: =D15*$F$46 -> 52499.611 | G15: =IFERROR(VLOOKUP(B:B,'Portfolio Snapshot'!$A:$L,4,0),0) -> 51043.07 | H15: =F15-G15 -> 1456.5408 | I15: =D15-E15 -> 0.0019425733 | J15: =IFERROR(VLOOKUP(B15,'Daily Change'!A:F,5,FALSE),"") -> 0 | K15: =IFERROR(VLOOKUP(B15,'Portfolio Snapshot'!$A:$L,12,),"") -> 0.36090985
C16: {=_xlfn.IFS(I16>0,"Underweight",I16=0,"",I16<0,"Overweight")} -> Underweight | D16: =SUM(D14:D15) -> 0.14 | E16: =SUM(E14:E15) -> 0.068057427 | F16: =SUM(F14:F15) -> 104999.22 | G16: =IFERROR(VLOOKUP(B:B,'Portfolio Snapshot'!$A:$L,4,0),0) -> 0 | H16: =F16-G16 -> 104999.22 | I16: =D16-E16 -> 0.071942573 | J16: =IFERROR(VLOOKUP(B16,'Daily Change'!A:F,5,FALSE),"") | K16: =IFERROR(VLOOKUP(B16,'Portfolio Snapshot'!$A:$L,12,),"")
K17: =IFERROR(VLOOKUP(B17,'Portfolio Snapshot'!$A:$L,12,),"")
A18: Satelites | D18: =D21+D29+D43 -> 0.37 | J18: =IFERROR(VLOOKUP(B18,'Daily Change'!A:F,5,FALSE),"") | K18: =IFERROR(VLOOKUP(B18,'Portfolio Snapshot'!$A:$L,12,),"")
A19: Theta/Income/Dividend | J19: =IFERROR(VLOOKUP(B19,'Daily Change'!A:F,5,FALSE),"") | K19: =IFERROR(VLOOKUP(B19,'Portfolio Snapshot'!$A:$L,12,),"")
A20: Alpha Architect 1-3 Month Box ET | B20: BOXX | C20: {=_xlfn.IFS(I20>0,"Underweight",I20=0,"",I20<0,"Overweight")} -> Overweight | D20: 0.03 | E20: =G20/$G$47 -> 0.3814128 | F20: =D20*$F$46 -> 22499.833 | G20: =IFERROR(VLOOKUP(B:B,'Portfolio Snapshot'!$A:$L,4,0),0) -> 286059.6 | H20: =F20-G20 -> -263559.77 | I20: =D20-E20 -> -0.3514128 | J20: =IFERROR(VLOOKUP(B20,'Daily Change'!A:F,5,FALSE),"") -> 0.00016992353 | K20: =IFERROR(VLOOKUP(B20,'Portfolio Snapshot'!$A:$L,12,),"") -> 0.0032998883
C21: {=_xlfn.IFS(I21>0,"Underweight",I21=0,"",I21<0,"Overweight")} -> Overweight | D21: =SUM(D20:D20) -> 0.03 | E21: =SUM(E20:E20) -> 0.3814128 | F21: =SUM(F20:F20) -> 22499.833 | G21: =SUM(G20:G20) -> 286059.6 | H21: =F21-G21 -> -263559.77 | I21: =D21-E21 -> -0.3514128 | J21: =IFERROR(VLOOKUP(B21,'Daily Change'!A:F,5,FALSE),"") | K21: =IFERROR(VLOOKUP(B21,'Portfolio Snapshot'!$A:$L,12,),"")
A22: Momentum/Trend Following | J22: =IFERROR(VLOOKUP(B22,'Daily Change'!A:F,5,FALSE),"") | K22: =IFERROR(VLOOKUP(B22,'Portfolio Snapshot'!$A:$L,12,),"")
A23: Wolfspeed | B23: WOLF | C23: {=_xlfn.IFS(I23>0,"Underweight",I23=0,"",I23<0,"Overweight")} -> Underweight | D23: 0.03 | E23: =G23/$G$47 -> 0.022072 | F23: =D23*$F$46 -> 22499.833 | G23: =IFERROR(VLOOKUP(B:B,'Portfolio Snapshot'!$A:$L,4,0),0) -> 16554 | H23: =F23-G23 -> 5945.8332 | I23: =D23-E23 -> 0.007928 | J23: =IFERROR(VLOOKUP(B23,'Daily Change'!A:F,5,FALSE),"") -> 0.095275903 | K23: =IFERROR(VLOOKUP(B23,'Portfolio Snapshot'!$A:$L,12,),"") -> -0.6106211
A24: Digi Power X | B24: DGXX | C24: {=_xlfn.IFS(I24>0,"Underweight",I24=0,"",I24<0,"Overweight")} -> Underweight | D24: 0.03 | E24: =G24/$G$47 -> 0.0175 | F24: =D24*$F$46 -> 22499.833 | G24: =IFERROR(VLOOKUP(B:B,'Portfolio Snapshot'!$A:$L,4,0),0) -> 13125 | H24: =F24-G24 -> 9374.8332 | I24: =D24-E24 -> 0.0125 | J24: =IFERROR(VLOOKUP(B24,'Daily Change'!A:F,5,FALSE),"") -> 0 | K24: =IFERROR(VLOOKUP(B24,'Portfolio Snapshot'!$A:$L,12,),"") -> -0.57765378
A25: On Semiconductor | B25: ON | C25: {=_xlfn.IFS(I25>0,"Underweight",I25=0,"",I25<0,"Overweight")} -> Underweight | D25: 0.03 | E25: =G25/$G$47 -> 0.0250656 | F25: =D25*$F$46 -> 22499.833 | G25: =IFERROR(VLOOKUP(B:B,'Portfolio Snapshot'!$A:$L,4,0),0) -> 18799.2 | H25: =F25-G25 -> 3700.6332 | I25: =D25-E25 -> 0.0049344 | J25: =IFERROR(VLOOKUP(B25,'Daily Change'!A:F,5,FALSE),"") -> 0.018463139 | K25: =IFERROR(VLOOKUP(B25,'Portfolio Snapshot'!$A:$L,12,),"") -> -0.22954098
A26: Intel Corporation | B26: INTC | C26: {=_xlfn.IFS(I26>0,"Underweight",I26=0,"",I26<0,"Overweight")} -> Underweight | D26: 0.03 | E26: =G26/$G$47 -> 0 | F26: =D26*$F$46 -> 22499.833 | G26: =IFERROR(VLOOKUP(B:B,'Portfolio Snapshot'!$A:$L,4,0),0) -> 0 | H26: =F26-G26 -> 22499.833 | I26: =D26-E26 -> 0.03 | J26: =IFERROR(VLOOKUP(B26,'Daily Change'!A:F,5,FALSE),"") -> -0.01236889 | K26: =IFERROR(VLOOKUP(B26,'Portfolio Snapshot'!$A:$L,12,),"")
A27: Towa Corporation | B27: 6315.T | C27: {=_xlfn.IFS(I27>0,"Underweight",I27=0,"",I27<0,"Overweight")} -> Underweight | D27: 0.02 | E27: =G27/$G$47 -> 0 | F27: =D27*$F$46 -> 14999.889 | G27: =IFERROR(VLOOKUP(B:B,'Portfolio Snapshot'!$A:$L,4,0),0) -> 0 | H27: =F27-G27 -> 14999.889 | I27: =D27-E27 -> 0.02 | J27: =IFERROR(VLOOKUP(B27,'Daily Change'!A:F,5,FALSE),"") | K27: =IFERROR(VLOOKUP(B27,'Portfolio Snapshot'!$A:$L,12,),"")
A28: JPMorgan Chase & Co | B28: JPM | C28: {=_xlfn.IFS(I28>0,"Underweight",I28=0,"",I28<0,"Overweight")} -> Underweight | D28: 0.02 | E28: =G28/$G$47 -> 0.0171024 | F28: =D28*$F$46 -> 14999.889 | G28: =IFERROR(VLOOKUP(B:B,'Portfolio Snapshot'!$A:$L,4,0),0) -> 12826.8 | H28: =F28-G28 -> 2173.0888 | I28: =D28-E28 -> 0.0028976 | J28: =IFERROR(VLOOKUP(B28,'Daily Change'!A:F,5,FALSE),"") -> -0.0081839439 | K28: =IFERROR(VLOOKUP(B28,'Portfolio Snapshot'!$A:$L,12,),"") -> 0.2705702
C29: {=_xlfn.IFS(I29>0,"Underweight",I29=0,"",I29<0,"Overweight")} -> Underweight | D29: =SUM(D23:D28) -> 0.16 | E29: =SUM(E23:E28) -> 0.08174 | F29: =SUM(F23:F28) -> 119999.11 | G29: =SUM(G23:G28) -> 61305 | H29: =F29-G29 -> 58694.11 | I29: =D29-E29 -> 0.07826 | J29: =IFERROR(VLOOKUP(B29,'Daily Change'!A:F,5,FALSE),"") | K29: =IFERROR(VLOOKUP(B29,'Portfolio Snapshot'!$A:$L,12,),"")
A30: Value/Quality/FD Growth | G30: =IFERROR(VLOOKUP(B:B,'Portfolio Snapshot'!$A:$L,4,0),0) -> 0 | J30: =IFERROR(VLOOKUP(B30,'Daily Change'!A:F,5,FALSE),"") | K30: =IFERROR(VLOOKUP(B30,'Portfolio Snapshot'!$A:$L,12,),"") | M30: =F21+F29+F43 -> 254998.11
B31: FOUR | C31: {=_xlfn.IFS(I31>0,"Underweight",I31=0,"",I31<0,"Overweight")} -> Underweight | D31: 0.02 | E31: =G31/$G$47 -> 0 | F31: =D31*$F$46 -> 14999.889 | G31: =IFERROR(VLOOKUP(B:B,'Portfolio Snapshot'!$A:$L,4,0),0) -> 0 | H31: =F31-G31 -> 14999.889 | I31: =D31-E31 -> 0.02 | J31: =IFERROR(VLOOKUP(B31,'Daily Change'!A:F,5,FALSE),"") -> -0.18677407 | K31: =IFERROR(VLOOKUP(B31,'Portfolio Snapshot'!$A:$L,12,),"")
A32: BE Semiconductor Industries | B32: BESI | C32: {=_xlfn.IFS(I32>0,"Underweight",I32=0,"",I32<0,"Overweight")} -> Underweight | D32: 0.02 | E32: =G32/$G$47 -> 0 | F32: =D32*$F$46 -> 14999.889 | G32: =IFERROR(VLOOKUP(B:B,'Portfolio Snapshot'!$A:$L,4,0),0) -> 0 | H32: =F32-G32 -> 14999.889 | I32: =D32-E32 -> 0.02 | J32: =IFERROR(VLOOKUP(B32,'Daily Change'!A:F,5,FALSE),"") -> -0.00092081031 | K32: =IFERROR(VLOOKUP(B32,'Portfolio Snapshot'!$A:$L,12,),"")
A33: Amazon.com | B33: AMZN | C33: {=_xlfn.IFS(I33>0,"Underweight",I33=0,"",I33<0,"Overweight")} -> Overweight | D33: 0.02 | E33: =G33/$G$47 -> 0.025410933 | F33: =D33*$F$46 -> 14999.889 | G33: =IFERROR(VLOOKUP(B:B,'Portfolio Snapshot'!$A:$L,4,0),0) -> 19058.2 | H33: =F33-G33 -> -4058.3112 | I33: =D33-E33 -> -0.0054109333 | J33: =IFERROR(VLOOKUP(B33,'Daily Change'!A:F,5,FALSE),"") -> -0.0014304053 | K33: =IFERROR(VLOOKUP(B33,'Portfolio Snapshot'!$A:$L,12,),"") -> 0.26492366
A34: PDF Solutions | B34: PDFS | C34: {=_xlfn.IFS(I34>0,"Underweight",I34=0,"",I34<0,"Overweight")} -> Overweight | D34: 0.03 | E34: =G34/$G$47 -> 0.067932 | F34: =D34*$F$46 -> 22499.833 | G34: =IFERROR(VLOOKUP(B:B,'Portfolio Snapshot'!$A:$L,4,0),0) -> 50949 | H34: =F34-G34 -> -28449.167 | I34: =D34-E34 -> -0.037932 | J34: =IFERROR(VLOOKUP(B34,'Daily Change'!A:F,5,FALSE),"") -> -0.071977355 | K34: =IFERROR(VLOOKUP(B34,'Portfolio Snapshot'!$A:$L,12,),"") -> 0.034329449
A35: Ciena Corp | B35: CIEN | C35: {=_xlfn.IFS(I35>0,"Underweight",I35=0,"",I35<0,"Overweight")} -> Underweight | D35: 0.03 | E35: =G35/$G$47 -> 0.019918827 | F35: =D35*$F$46 -> 22499.833 | G35: =IFERROR(VLOOKUP(B:B,'Portfolio Snapshot'!$A:$L,4,0),0) -> 14939.12 | H35: =F35-G35 -> 7560.7132 | I35: =D35-E35 -> 0.010081173 | J35: =IFERROR(VLOOKUP(B35,'Daily Change'!A:F,5,FALSE),"") -> -0.012401243 | K35: =IFERROR(VLOOKUP(B35,'Portfolio Snapshot'!$A:$L,12,),"") -> -0.25653827
A36: Semtech Corp | B36: SMTC | C36: {=_xlfn.IFS(I36>0,"Underweight",I36=0,"",I36<0,"Overweight")} -> Underweight | D36: 0.03 | E36: =G36/$G$47 -> 0 | F36: =D36*$F$46 -> 22499.833 | G36: =IFERROR(VLOOKUP(B:B,'Portfolio Snapshot'!$A:$L,4,0),0) -> 0 | H36: =F36-G36 -> 22499.833 | I36: =D36-E36 -> 0.03 | J36: =IFERROR(VLOOKUP(B36,'Daily Change'!A:F,5,FALSE),"") -> 0.11158763 | K36: =IFERROR(VLOOKUP(B36,'Portfolio Snapshot'!$A:$L,12,),"")
A37: Lumentum Holdings | B37: LITE | C37: {=_xlfn.IFS(I37>0,"Underweight",I37=0,"",I37<0,"Overweight")} -> Underweight | D37: 0.03 | E37: =G37/$G$47 -> 0.022348267 | F37: =D37*$F$46 -> 22499.833 | G37: =IFERROR(VLOOKUP(B:B,'Portfolio Snapshot'!$A:$L,4,0),0) -> 16761.2 | H37: =F37-G37 -> 5738.6332 | I37: =D37-E37 -> 0.0076517333 | J37: =IFERROR(VLOOKUP(B37,'Daily Change'!A:F,5,FALSE),"") -> 0.014281219 | K37: =IFERROR(VLOOKUP(B37,'Portfolio Snapshot'!$A:$L,12,),"") -> -0.081074561
A38: Wolfspeed | B38: WOLF | C38: {=_xlfn.IFS(I38>0,"Underweight",I38=0,"",I38<0,"Overweight")} -> Underweight | D38: 0.03 | E38: =G38/$G$47 -> 0.022072 | F38: =D38*$F$46 -> 22499.833 | G38: =IFERROR(VLOOKUP(B:B,'Portfolio Snapshot'!$A:$L,4,0),0) -> 16554 | H38: =F38-G38 -> 5945.8332 | I38: =D38-E38 -> 0.007928 | J38: =IFERROR(VLOOKUP(B38,'Daily Change'!A:F,5,FALSE),"") -> 0.095275903 | K38: =IFERROR(VLOOKUP(B38,'Portfolio Snapshot'!$A:$L,12,),"") -> -0.6106211
A39: Soitec | B39: SOI | C39: {=_xlfn.IFS(I39>0,"Underweight",I39=0,"",I39<0,"Overweight")} -> Underweight | D39: 0.03 | E39: =G39/$G$47 -> 0 | F39: =D39*$F$46 -> 22499.833 | G39: =IFERROR(VLOOKUP(B:B,'Portfolio Snapshot'!$A:$L,4,0),0) -> 0 | H39: =F39-G39 -> 22499.833 | I39: =D39-E39 -> 0.03 | J39: =IFERROR(VLOOKUP(B39,'Daily Change'!A:F,5,FALSE),"") -> -0.002484472 | K39: =IFERROR(VLOOKUP(B39,'Portfolio Snapshot'!$A:$L,12,),"")
A40: Texas Instrument | B40: TXN | C40: {=_xlfn.IFS(I40>0,"Underweight",I40=0,"",I40<0,"Overweight")} -> Overweight | D40: 0.03 | E40: =G40/$G$47 -> 0.048256 | F40: =D40*$F$46 -> 22499.833 | G40: =IFERROR(VLOOKUP(B:B,'Portfolio Snapshot'!$A:$L,4,0),0) -> 36192 | H40: =F40-G40 -> -13692.167 | I40: =D40-E40 -> -0.018256 | J40: =IFERROR(VLOOKUP(B40,'Daily Change'!A:F,5,FALSE),"") -> 0.0024485093 | K40: =IFERROR(VLOOKUP(B40,'Portfolio Snapshot'!$A:$L,12,),"") -> -0.065602974
A41: Zoom Communications | B41: ZM | C41: {=_xlfn.IFS(I41>0,"Underweight",I41=0,"",I41<0,"Overweight")} -> Underweight | D41: 0.03 | E41: =G41/$G$47 -> 0 | F41: =D41*$F$46 -> 22499.833 | G41: =IFERROR(VLOOKUP(B:B,'Portfolio Snapshot'!$A:$L,4,0),0) -> 0 | H41: =F41-G41 -> 22499.833 | I41: =D41-E41 -> 0.03 | J41: =IFERROR(VLOOKUP(B41,'Daily Change'!A:F,5,FALSE),"") -> 0.0065580286 | K41: =IFERROR(VLOOKUP(B41,'Portfolio Snapshot'!$A:$L,12,),"")
A42: Broadcom Inc | B42: AVGO | C42: {=_xlfn.IFS(I42>0,"Underweight",I42=0,"",I42<0,"Overweight")} -> Underweight | D42: 0.03 | E42: =G42/$G$47 -> 0 | F42: =D42*$F$46 -> 22499.833 | G42: =IFERROR(VLOOKUP(B:B,'Portfolio Snapshot'!$A:$L,4,0),0) -> 0 | H42: =F42-G42 -> 22499.833 | I42: =D42-E42 -> 0.03 | J42: =IFERROR(VLOOKUP(B42,'Daily Change'!A:F,5,FALSE),"") -> 0.0054628479 | K42: =IFERROR(VLOOKUP(B42,'Portfolio Snapshot'!$A:$L,12,),"")
C43: {=_xlfn.IFS(I43>0,"Underweight",I43=0,"",I43<0,"Overweight")} -> Underweight | D43: =SUM(D31:D37) -> 0.18 | E43: =SUM(E31:E36) -> 0.11326176 | F43: =SUM(F31:F36) -> 112499.17 | G43: =SUM(G31:G36) -> 84946.32 | H43: =F43-G43 -> 27552.846 | I43: =D43-E43 -> 0.06673824 | J43: =IFERROR(VLOOKUP(B43,'Daily Change'!A:F,5,FALSE),"") | K43: =IFERROR(VLOOKUP(B43,'Portfolio Snapshot'!$A:$L,12,),"")
A44: Others | J44: =IFERROR(VLOOKUP(B44,'Daily Change'!A:F,5,FALSE),"") | K44: =IFERROR(VLOOKUP(B44,'Portfolio Snapshot'!$A:$L,12,),"")
A45: Cash | C45: {=_xlfn.IFS(I45>0,"Underweight",I45=0,"",I45<0,"Overweight")} -> Overweight | D45: 0 | E45: =G45/$G$47 -> 0.12053004 | F45: =D45*$G$47 -> 0 | G45: ='Portfolio Snapshot'!D20 -> 90397.53 | H45: =F45-G45 -> -90397.53 | I45: =D45-E45 -> -0.12053004 | J45: =IFERROR(VLOOKUP(B45,'Daily Change'!A:F,5,FALSE),"") | K45: =IFERROR(VLOOKUP(B45,'Portfolio Snapshot'!$A:$L,12,),"")
A46: Total | D46: =SUM(D45+D18,D2) -> 0.97 | E46: =SUM(E45,E43,E29,E21,E16,E12) -> 1.0545094 | F46: =Subscription!C10 -> 749994.44 | G46: =SUM(G45,G43,G29,G21,G16,G12) -> 739838.98 | H46: =SUM(H45,H43,H29,H21,H16,H12) -> -34844.206 | I46: =SUM(I45,I43,I29,I21,I16,I12) -> -0.0845094 | J46: =IFERROR(VLOOKUP(B46,'Daily Change'!$B$1:$E$12,10,FALSE),"") | K46: =IFERROR(VLOOKUP(B46,'Portfolio Snapshot'!$A:$L,11,),"")
G47: 750000

Sheet Daily Change
A1: SYMBOL | B1: NAME | C1: CURRENT | D1: Previous Close | E1: price change | F1: Beta
A2: {=_FV(B2,"Ticker symbol",TRUE)} -> GE | B2: #VALUE! | C2: {=_FV(B2,"Price")} -> 374.55 | D2: {=_FV(B2,"Previous close",TRUE)} -> 381.22 | E2: =C2/D2 -1 -> -0.017496459 | F2: {=_FV(B2,"Beta")} -> 1.3818
A3: {=_FV(B3,"Ticker symbol",TRUE)} -> ITB | B3: #VALUE! | C3: {=_FV(B3,"Price")} -> 98.53 | D3: {=_FV(B3,"Previous close",TRUE)} -> 100.88 | E3: =C3/D3 -1 -> -0.023295004 | F3: {=_FV(B3,"Beta")} -> 1.369
A4: {=_FV(B4,"Ticker symbol",TRUE)} -> FISV | B4: #VALUE! | C4: {=_FV(B4,"Price")} -> 54.11 | D4: {=_FV(B4,"Previous close",TRUE)} -> 54.11 | E4: =C4/D4 -1 -> 0 | F4: {=_FV(B4,"Beta")} -> 0.7975
A5: {=_FV(B5,"Ticker symbol",TRUE)} -> OXY | B5: #VALUE! | C5: {=_FV(B5,"Price")} -> 56.04 | D5: {=_FV(B5,"Previous close",TRUE)} -> 53.81 | E5: =C5/D5 -1 -> 0.041442111 | F5: {=_FV(B5,"Beta")} -> 0.1466
A6: {=_FV(B6,"Ticker symbol",TRUE)} -> APH | B6: #VALUE! | C6: {=_FV(B6,"Price")} -> 170.61 | D6: {=_FV(B6,"Previous close",TRUE)} -> 172.24 | E6: =C6/D6 -1 -> -0.0094635392 | F6: {=_FV(B6,"Beta")} -> 1.2535
A7: {=_FV(B7,"Ticker symbol",TRUE)} -> XLE | B7: #VALUE! | C7: {=_FV(B7,"Price")} -> 58.16 | D7: {=_FV(B7,"Previous close",TRUE)} -> 57.31 | E7: =C7/D7 -1 -> 0.014831618 | F7: {=_FV(B7,"Beta")} -> 1.08
A8: {=_FV(B8,"Ticker symbol",TRUE)} -> NVDA | B8: #VALUE! | C8: {=_FV(B8,"Price")} -> 218.99 | D8: {=_FV(B8,"Previous close",TRUE)} -> 219.22 | E8: =C8/D8 -1 -> -0.0010491743 | F8: {=_FV(B8,"Beta")} -> 2.2139
A9: {=_FV(B9,"Ticker symbol",TRUE)} -> DHR | B9: #VALUE! | C9: {=_FV(B9,"Price")} -> 199.98 | D9: {=_FV(B9,"Previous close",TRUE)} -> 199.66 | E9: =C9/D9 -1 -> 0.0016027246 | F9: {=_FV(B9,"Beta")} -> 0.7731
A10: {=_FV(B10,"Ticker symbol",TRUE)} -> XLU | B10: #VALUE! | C10: {=_FV(B10,"Price")} -> 43.38 | D10: {=_FV(B10,"Previous close",TRUE)} -> 43.66 | E10: =C10/D10 -1 -> -0.0064131929 | F10: {=_FV(B10,"Beta")} -> 0.9979
A11: {=_FV(B11,"Ticker symbol",TRUE)} -> BRK.B | B11: #VALUE! | C11: {=_FV(B11,"Price")} -> 524.61 | D11: {=_FV(B11,"Previous close",TRUE)} -> 518.85 | E11: =C11/D11 -1 -> 0.011101474 | F11: {=_FV(B11,"Beta")} -> 0.6056
A12: {=_FV(B12,"Ticker symbol",TRUE)} -> OTIS | B12: #VALUE! | C12: {=_FV(B12,"Price")} -> 73.83 | D12: {=_FV(B12,"Previous close",TRUE)} -> 73.1 | E12: =C12/D12 -1 -> 0.0099863201 | F12: {=_FV(B12,"Beta")} -> 0.8787
A13: {=_FV(B13,"Ticker symbol",TRUE)} -> V | B13: #VALUE! | C13: {=_FV(B13,"Price")} -> 370.47 | D13: {=_FV(B13,"Previous close",TRUE)} -> 368.54 | E13: =C13/D13 -1 -> 0.0052368807 | F13: {=_FV(B13,"Beta")} -> 0.7558
... A36: {=_FV(B36,"Ticker symbol",TRUE)} -> VOT | B36: #VALUE! | C36: {=_FV(B36,"Price")} -> 302.03 | D36: {=_FV(B36,"Previous close",TRUE)} -> 302.03 | E36: =C36/D36 -1 -> 0 | F36: {=_FV(B36,"Beta")} -> 0.9247
B37: #VALUE! | C37: {=_FV(B37,"Price")} -> 7709.96 | D37: {=_FV(B37,"Previous close",TRUE)} -> 7723.55 | E37: =C37/D37 -1 -> -0.0017595536
A38: URTH | B38: #VALUE! | C38: {=_FV(B38,"Price")} -> 208.63 | D38: {=_FV(B38,"Previous close",TRUE)} -> 209.15 | E38: =C38/D38 -1 -> -0.0024862539
B39: #VALUE! | C39: {=_FV(B39,"Price")} -> 147.91 | D39: {=_FV(B39,"Previous close",TRUE)} -> 147.63 | E39: =C39/D39 -1 -> 0.0018966335 | F39: {=_FV(B39,"Beta")} -> 0.9986
A40: {=_FV(B40,"Ticker symbol",TRUE)} -> IDEV | B40: #VALUE! | C40: {=_FV(B40,"Price")} -> 92.28 | D40: {=_FV(B40,"Previous close",TRUE)} -> 92.28 | E40: =C40/D40 -1 -> 0 | F40: {=_FV(B40,"Beta")} -> 0.9599
A41: {=_FV(B41,"Ticker symbol",TRUE)} -> VVIAX | B41: #VALUE! | C41: {=_FV(B41,"Price")} -> 87.15 | D41: {=_FV(B41,"Previous close",TRUE)} -> 87.39 | E41: =C41/D41 -1 -> -0.0027463096
A42: {=_FV(B42,"Ticker symbol",TRUE)} -> MSFT | B42: #VALUE! | C42: {=_FV(B42,"Price")} -> 499.86 | D42: {=_FV(B42,"Previous close",TRUE)} -> 487.46 | E42: =C42/D42 -1 -> 0.025437985 | F42: {=_FV(B42,"Beta")} -> 1.1022
A43: {=_FV(B43,"Ticker symbol",TRUE)} -> VBR | B43: #VALUE! | C43: {=_FV(B43,"Price")} -> 248.41 | D43: {=_FV(B43,"Previous close",TRUE)} -> 248.41 | E43: =C43/D43 -1 -> 0 | F43: {=_FV(B43,"Beta")} -> 0.9832
A44: {=_FV(B44,"Ticker symbol",TRUE)} -> ECC | B44: #VALUE! | C44: {=_FV(B44,"Price")} -> 3.9 | D44: {=_FV(B44,"Previous close",TRUE)} -> 3.86 | E44: =C44/D44 -1 -> 0.010362694 | F44: {=_FV(B44,"Beta")} -> #VALUE!
A45: {=_FV(B45,"Ticker symbol",TRUE)} -> SPOT | B45: #VALUE! | C45: {=_FV(B45,"Price")} -> 475.07 | D45: {=_FV(B45,"Previous close",TRUE)} -> 482.23 | E45: =C45/D45 -1 -> -0.014847687 | F45: {=_FV(B45,"Beta")} -> 1.5651
A46: {=_FV(B46,"Ticker symbol",TRUE)} -> WMT | B46: #VALUE! | C46: {=_FV(B46,"Price")} -> 112.07 | D46: {=_FV(B46,"Previous close",TRUE)} -> 112.34 | E46: =C46/D46 -1 -> -0.0024034182 | F46: {=_FV(B46,"Beta")} -> 0.6027
A47: {=_FV(B47,"Ticker symbol",TRUE)} -> KO | B47: #VALUE! | C47: {=_FV(B47,"Price")} -> 86.85 | D47: {=_FV(B47,"Previous close",TRUE)} -> 86.83 | E47: =C47/D47 -1 -> 0.00023033514 | F47: {=_FV(B47,"Beta")} -> 0.3383
A48: {=_FV(B48,"Ticker symbol",TRUE)} -> INCY | B48: #VALUE! | C48: {=_FV(B48,"Price")} -> 118.38 | D48: {=_FV(B48,"Previous close",TRUE)} -> 119.8 | E48: =C48/D48 -1 -> -0.011853088 | F48: {=_FV(B48,"Beta")} -> 0.7648
A49: {=_FV(B49,"Ticker symbol",TRUE)} -> INDA | B49: #VALUE! | C49: {=_FV(B49,"Price")} -> 50.12 | D49: {=_FV(B49,"Previous close",TRUE)} -> 50.31 | E49: =C49/D49 -1 -> -0.0037765852 | F49: {=_FV(B49,"Beta")} -> 0.8058
A50: {=_FV(B50,"Ticker symbol",TRUE)} -> IXC | B50: #VALUE! | C50: {=_FV(B50,"Price")} -> 54.13 | D50: {=_FV(B50,"Previous close",TRUE)} -> 53.43 | E50: =C50/D50 -1 -> 0.013101254 | F50: {=_FV(B50,"Beta")} -> 1.0149
A51: {=_FV(B51,"Ticker symbol",TRUE)} -> SPMO | B51: #VALUE! | C51: {=_FV(B51,"Price")} -> 149.1 | D51: {=_FV(B51,"Previous close",TRUE)} -> 150.27 | E51: =C51/D51 -1 -> -0.0077859852 | F51: {=_FV(B51,"Beta")} -> 1.0795
A52: {=_FV(B52,"Ticker symbol",TRUE)} -> FOUR | B52: #VALUE! | C52: {=_FV(B52,"Price")} -> 43.41 | D52: {=_FV(B52,"Previous close",TRUE)} -> 53.38 | E52: =C52/D52 -1 -> -0.18677407 | F52: {=_FV(B52,"Beta")} -> 1.4035
A53: {=_FV(B53,"Ticker symbol",TRUE)} -> VTV | B53: #VALUE! | C53: {=_FV(B53,"Price")} -> 223.37 | D53: {=_FV(B53,"Previous close",TRUE)} -> 223.99 | E53: =C53/D53 -1 -> -0.0027679807 | F53: {=_FV(B53,"Beta")} -> 0.886
... A55: {=_FV(B55,"Ticker symbol",TRUE)} -> TEM | B55: #VALUE! | C55: {=_FV(B55,"Price")} -> 46.12 | D55: {=_FV(B55,"Previous close",TRUE)} -> 46.7 | E55: =C55/D55 -1 -> -0.0124197 | F55: {=_FV(B55,"Beta")} -> 3.149
A56: {=_FV(B56,"Ticker symbol",TRUE)} -> JEPQ | B56: #VALUE! | C56: {=_FV(B56,"Price")} -> 59.34 | D56: {=_FV(B56,"Previous close",TRUE)} -> 59.38 | E56: =C56/D56 -1 -> -0.00067362748
A57: {=_FV(B57,"Ticker symbol",TRUE)} -> CEG | B57: #VALUE! | C57: {=_FV(B57,"Price")} -> 261.1 | D57: {=_FV(B57,"Previous close",TRUE)} -> 265.12 | E57: =C57/D57 -1 -> -0.015162945
A58: {=_FV(B58,"Ticker symbol",TRUE)} -> FEZ | B58: #VALUE! | C58: {=_FV(B58,"Price")} -> 71.22 | D58: {=_FV(B58,"Previous close",TRUE)} -> 71.22 | E58: =C58/D58 -1 -> 0 | F58: {=_FV(B58,"Beta")} -> 1.0878
A59: {=_FV(B59,"Ticker symbol",TRUE)} -> KO | B59: #VALUE! | C59: {=_FV(B59,"Price")} -> 86.85 | D59: {=_FV(B59,"Previous close",TRUE)} -> 86.83 | E59: =C59/D59 -1 -> 0.00023033514
A60: {=_FV(B60,"Ticker symbol",TRUE)} -> MDLZ | B60: #VALUE! | C60: {=_FV(B60,"Price")} -> 62.75 | D60: {=_FV(B60,"Previous close",TRUE)} -> 62.6 | E60: =C60/D60 -1 -> 0.0023961661 | F60: {=_FV(B60,"Beta")} -> 0.4034
A61: {=_FV(B61,"Ticker symbol",TRUE)} -> ARLP | B61: #VALUE! | C61: {=_FV(B61,"Price")} -> 25.32 | D61: {=_FV(B61,"Previous close",TRUE)} -> 25.4 | E61: =C61/D61 -1 -> -0.0031496063
A62: {=_FV(B62,"Ticker symbol",TRUE)} -> BYDDY | B62: #VALUE! | C62: {=_FV(B62,"Price")} -> 11.48 | D62: {=_FV(B62,"Previous close",TRUE)} -> 11.78 | E62: =C62/D62 -1 -> -0.025466893 | F62: {=_FV(B62,"Beta")} -> 0.5323
A63: {=_FV(B63,"Ticker symbol",TRUE)} -> HAGHY | B63: #VALUE! | C63: {=_FV(B63,"Price")} -> 10.32 | D63: {=_FV(B63,"Previous close",TRUE)} -> 9.9 | E63: =C63/D63 -1 -> 0.042424242 | F63: {=_FV(B63,"Beta")} -> 0.4279
A64: {=_FV(B64,"Ticker symbol",TRUE)} -> GLD | B64: #VALUE! | C64: {=_FV(B64,"Price")} -> 389.67 | D64: {=_FV(B64,"Previous close",TRUE)} -> 389.64 | E64: =C64/D64 -1 -> 7.6994148e-05 | F64: {=_FV(B64,"Beta")} -> 0.8287
A65: META | B65: #VALUE! | C65: {=_FV(B65,"Price")} -> 589.9 | D65: {=_FV(B65,"Previous close",TRUE)} -> 588.77 | E65: =C65/D65 -1 -> 0.0019192554 | F65: {=_FV(B65,"Beta")} -> 1.2462
A66: {=_FV(B66,"Ticker symbol",TRUE)} -> TJX | B66: #VALUE! | C66: {=_FV(B66,"Price")} -> 162.06 | D66: {=_FV(B66,"Previous close",TRUE)} -> 159.92 | E66: =C66/D66 -1 -> 0.013381691 | F66: {=_FV(B66,"Beta")} -> 0.6142
A67: {=_FV(B67,"Ticker symbol",TRUE)} -> UBER | B67: #VALUE! | C67: {=_FV(B67,"Price")} -> 70.47 | D67: {=_FV(B67,"Previous close",TRUE)} -> 68.18 | E67: =C67/D67 -1 -> 0.033587562 | F67: {=_FV(B67,"Beta")} -> 1.1411
A68: {=_FV(B68,"Ticker symbol",TRUE)} -> VST | B68: #VALUE! | C68: {=_FV(B68,"Price")} -> 141.38 | D68: {=_FV(B68,"Previous close",TRUE)} -> 140.58 | E68: =C68/D68 -1 -> 0.0056907099 | F68: {=_FV(B68,"Beta")} -> 1.4107
A69: {=_FV(B69,"Ticker symbol",TRUE)} -> AAPL | B69: #VALUE! | C69: {=_FV(B69,"Price")} -> 312.41 | D69: {=_FV(B69,"Previous close",TRUE)} -> 311 | E69: =C69/D69 -1 -> 0.0045337621 | F69: {=_FV(B69,"Beta")} -> 1.081
A70: {=_FV(B70,"Ticker symbol",TRUE)} -> ROKU | B70: #VALUE! | C70: {=_FV(B70,"Price")} -> 150.07 | D70: {=_FV(B70,"Previous close",TRUE)} -> 146.96 | E70: =C70/D70 -1 -> 0.021162221 | F70: {=_FV(B70,"Beta")} -> 2.0382
A71: {=_FV(B71,"Ticker symbol",TRUE)} -> WMT | B71: #VALUE! | C71: {=_FV(B71,"Price")} -> 112.07 | D71: {=_FV(B71,"Previous close",TRUE)} -> 112.34 | E71: =C71/D71 -1 -> -0.0024034182 | F71: {=_FV(B71,"Beta")} -> 0.6027
A72: {=_FV(B72,"Ticker symbol",TRUE)} -> BABA | B72: #VALUE! | C72: {=_FV(B72,"Price")} -> 126.81 | D72: {=_FV(B72,"Previous close",TRUE)} -> 128.53 | E72: =C72/D72 -1 -> -0.01338209 | F72: {=_FV(B72,"Beta")} -> 0.5204
A73: {=_FV(B73,"Ticker symbol",TRUE)} -> XPEV | B73: #VALUE! | C73: {=_FV(B73,"Price")} -> 11.68 | D73: {=_FV(B73,"Previous close",TRUE)} -> 11.75 | E73: =C73/D73 -1 -> -0.0059574468 | F73: {=_FV(B73,"Beta")} -> 1.0993
A74: {=_FV(B74,"Ticker symbol",TRUE)} -> NVAX | B74: #VALUE! | C74: {=_FV(B74,"Price")} -> 7.74 | D74: {=_FV(B74,"Previous close",TRUE)} -> 7.7 | E74: =C74/D74 -1 -> 0.0051948052 | F74: {=_FV(B74,"Beta")} -> 2.4188
A75: {=_FV(B75,"Ticker symbol",TRUE)} -> KTOS | B75: #VALUE! | C75: {=_FV(B75,"Price")} -> 57.41 | D75: {=_FV(B75,"Previous close",TRUE)} -> 55.34 | E75: =C75/D75 -1 -> 0.037405132 | F75: {=_FV(B75,"Beta")} -> 1.1301
A76: {=_FV(B76,"Ticker symbol",TRUE)} -> EWG | B76: #VALUE! | C76: {=_FV(B76,"Price")} -> 43.52 | D76: {=_FV(B76,"Previous close",TRUE)} -> 43.52 | E76: =C76/D76 -1 -> 0 | F76: {=_FV(B76,"Beta")} -> 1.0827
A77: {=_FV(B77,"Ticker symbol",TRUE)} -> PLMR | B77: #VALUE! | C77: {=_FV(B77,"Price")} -> 136.82 | D77: {=_FV(B77,"Previous close",TRUE)} -> 134 | E77: =C77/D77 -1 -> 0.021044776 | F77: {=_FV(B77,"Beta")} -> 0.382
... A87: {=_FV(B87,"Ticker symbol",TRUE)} -> BX | B87: #VALUE! | C87: {=_FV(B87,"Price")} -> 133.45 | D87: {=_FV(B87,"Previous close",TRUE)} -> 136.03 | E87: =C87/D87 -1 -> -0.018966404 | F87: {=_FV(B87,"Beta")} -> 1.5505
A88: BESI | B88: #VALUE! | C88: {=_FV(B88,"Price")} -> 217 | D88: {=_FV(B88,"Previous close",TRUE)} -> 217.2 | E88: =C88/D88 -1 -> -0.00092081031 | F88: {=_FV(B88,"Beta")} -> 1.8701
A89: SMTC | B89: #VALUE! | C89: {=_FV(B89,"Price")} -> 134.78 | D89: {=_FV(B89,"Previous close",TRUE)} -> 121.25 | E89: =C89/D89 -1 -> 0.11158763 | F89: {=_FV(B89,"Beta")} -> 2.3353
A90: INTC | B90: #VALUE! | C90: {=_FV(B90,"Price")} -> 99.81 | D90: {=_FV(B90,"Previous close",TRUE)} -> 101.06 | E90: =C90/D90 -1 -> -0.01236889 | F90: {=_FV(B90,"Beta")} -> 2.2482
A91: LITE | B91: #VALUE! | C91: {=_FV(B91,"Price")} -> 838.06 | D91: {=_FV(B91,"Previous close",TRUE)} -> 826.26 | E91: =C91/D91 -1 -> 0.014281219 | F91: {=_FV(B91,"Beta")} -> 1.5259
A92: WOLF | B92: #VALUE! | C92: {=_FV(B92,"Price")} -> 27.59 | D92: {=_FV(B92,"Previous close",TRUE)} -> 25.19 | E92: =C92/D92 -1 -> 0.095275903 | F92: {=_FV(B92,"Beta")} -> 5.577
A93: AVGO | B93: #VALUE! | C93: {=_FV(B93,"Price")} -> 420.565 | D93: {=_FV(B93,"Previous close",TRUE)} -> 418.28 | E93: =C93/D93 -1 -> 0.0054628479 | F93: {=_FV(B93,"Beta")} -> 1.473
A94: SITM | B94: #VALUE! | C94: {=_FV(B94,"Price")} -> 687.5 | D94: {=_FV(B94,"Previous close",TRUE)} -> 543.12 | E94: =C94/D94 -1 -> 0.26583444 | F94: {=_FV(B94,"Beta")} -> 2.8507
A95: BE | B95: #VALUE! | C95: {=_FV(B95,"Price")} -> 228.96 | D95: {=_FV(B95,"Previous close",TRUE)} -> 234.33 | E95: =C95/D95 -1 -> -0.0229164 | F95: {=_FV(B95,"Beta")} -> 3.8252
A96: BOXX | B96: #VALUE! | C96: {=_FV(B96,"Price")} -> 117.72 | D96: {=_FV(B96,"Previous close",TRUE)} -> 117.7 | E96: =C96/D96 -1 -> 0.00016992353 | F96: {=_FV(B96,"Beta")} -> 0.4974
A97: NVMI | B97: #VALUE! | C97: {=_FV(B97,"Price")} -> 381.32 | D97: {=_FV(B97,"Previous close",TRUE)} -> 402.38 | E97: =C97/D97 -1 -> -0.052338585 | F97: {=_FV(B97,"Beta")} -> 1.7708
A98: BOXX | B98: #VALUE! | C98: {=_FV(B98,"Price")} -> 117.72 | D98: {=_FV(B98,"Previous close",TRUE)} -> 117.7 | E98: =C98/D98 -1 -> 0.00016992353 | F98: {=_FV(B98,"Beta")} -> 0.4974
A99: JEPI | B99: #VALUE! | C99: {=_FV(B99,"Price")} -> 57.59 | D99: {=_FV(B99,"Previous close",TRUE)} -> 57.51 | E99: =C99/D99 -1 -> 0.0013910624 | F99: {=_FV(B99,"Beta")} -> 0.4005
... A103: PDFS | B103: #VALUE! | C103: {=_FV(B103,"Price")} -> 45.9 | D103: {=_FV(B103,"Previous close",TRUE)} -> 49.46 | E103: =C103/D103 -1 -> -0.071977355 | F103: {=_FV(B103,"Beta")} -> 1.6476
B104: #VALUE! | C104: {=_FV(B104,"Price")} -> 1.152 | D104: {=_FV(B104,"Previous close",TRUE)} -> 1.1524 | E104: =C104/D104 -1 -> -0.0003471017 | F104: {=_FV(B104,"Beta")} -> #VALUE!
A105: ON | B105: #VALUE! | C105: {=_FV(B105,"Price")} -> 78.33 | D105: {=_FV(B105,"Previous close",TRUE)} -> 76.91 | E105: =C105/D105 -1 -> 0.018463139 | F105: {=_FV(B105,"Beta")} -> 1.9949
A106: STM | B106: #VALUE! | C106: {=_FV(B106,"Price")} -> 53.28 | D106: {=_FV(B106,"Previous close",TRUE)} -> 52.77 | E106: =C106/D106 -1 -> 0.0096645821 | F106: {=_FV(B106,"Beta")} -> 1.9385
A107: TXN | B107: #VALUE! | C107: {=_FV(B107,"Price")} -> 278.4 | D107: {=_FV(B107,"Previous close",TRUE)} -> 277.72 | E107: =C107/D107 -1 -> 0.0024485093 | F107: {=_FV(B107,"Beta")} -> 1.3201
A108: IFX | B108: #VALUE! | C108: {=_FV(B108,"Price")} -> 61.38 | D108: {=_FV(B108,"Previous close",TRUE)} -> 60.55 | E108: =C108/D108 -1 -> 0.01370768 | F108: {=_FV(B108,"Beta")} -> 2.0617
A109: DGXX | B109: #VALUE! | C109: {=_FV(B109,"Price")} -> 3.75 | D109: {=_FV(B109,"Previous close",TRUE)} -> 3.75 | E109: =C109/D109 -1 -> 0 | F109: {=_FV(B109,"Beta")} -> 7.0902

Sheet PivotSource
A1: Quarter | B1: Date | C1: Fund Return | D1: Benchmark Return | E1: Month | F1: Year
A2: 3 | B2: 45475 | C2: 0 | D2: 0 | E2: Jul | F2: 2024
A3: 3 | B3: 45476 | C3: -0.0048349373 | D3: 0.0067976847 | E3: Jul | F3: 2024
A4: 3 | B4: 45477 | C4: 0 | D4: 0 | E4: Jul | F4: 2024
A5: 3 | B5: 45478 | C5: 0.00043064953 | D5: 0.0060832943 | E5: Jul | F5: 2024
A6: 3 | B6: 45479 | C6: 0 | D6: 0 | E6: Jul | F6: 2024
A7: 3 | B7: 45480 | C7: 0 | D7: 0 | E7: Jul | F7: 2024
A8: 3 | B8: 45481 | C8: -0.00057500095 | D8: -0.0010631229 | E8: Jul | F8: 2024
A9: 3 | B9: 45482 | C9: 0.00042572448 | D9: 0.00059864308 | E9: Jul | F9: 2024
A10: 3 | B10: 45483 | C10: 0.0017367714 | D10: 0.0105697 | E10: Jul | F10: 2024
A11: 3 | B11: 45484 | C11: 0.0045714095 | D11: -0.0049335614 | E11: Jul | F11: 2024
A12: 3 | B12: 45485 | C12: 0.0036253039 | D12: 0.0074700866 | E12: Jul | F12: 2024
A13: 3 | B13: 45486 | C13: 0 | D13: 0 | E13: Jul | F13: 2024
... A646: 2 | B646: 46119 | C646: 0.012005792 | D646: -0.00027394258 | E646: Apr | F646: 2026
